{
  "SPDXID": "SPDXRef-DOCUMENT",
  "name": "falcosecurity/pigeon v0.2.1",
  "spdxVersion": "SPDX-2.3",
  "creationInfo": {
    "created": "2026-02-14T02:51:45Z",
    "creators": [
      "Tool: bom-v0.7.1",
      "Tool: cncf-automation-sbom-generator"
    ],
    "licenseListVersion": "3.27",
    "comment": "SBOM for CNCF project: falcosecurity/pigeon@v0.2.1"
  },
  "dataLicense": "CC0-1.0",
  "documentNamespace": "https://github.com/falcosecurity/pigeon/releases/tag/v0.2.1",
  "documentDescribes": [
    "SPDXRef-Package-tmp.CvHgx0WVyh"
  ],
  "files": [
    {
      "SPDXID": "SPDXRef-File-tmp.CvHgx0WVyh-pkg-config-configC95test.go",
      "fileName": "pkg/config/config_test.go",
      "copyrightText": "NOASSERTION",
      "licenseConcluded": "Apache-2.0",
      "fileTypes": [
        "SOURCE"
      ],
      "licenseInfoInFiles": [
        "NONE"
      ],
      "checksums": [
        {
          "algorithm": "SHA256",
          "checksumValue": "6e0458cbcd187311a451b74a323b1cba179e615aa78810d0e61dd8b4ca6bebde"
        },
        {
          "algorithm": "SHA512",
          "checksumValue": "8d1864d1ef10a4110922067f1a3047f073ea95698fb5f14aa0fd8ffcfede3601865bce00a35660e55165481f9f3e00d6f41bfb8cc043d7078d25cbe8a223d672"
        },
        {
          "algorithm": "SHA1",
          "checksumValue": "0088de6594c5707e03ba9c3ee354d15f04498878"
        }
      ]
    },
    {
      "SPDXID": "SPDXRef-File-tmp.CvHgx0WVyh-pkg-poiana-secrets.go",
      "fileName": "pkg/poiana/secrets.go",
      "copyrightText": "NOASSERTION",
      "licenseConcluded": "Apache-2.0",
      "fileTypes": [
        "SOURCE"
      ],
      "licenseInfoInFiles": [
        "NONE"
      ],
      "checksums": [
        {
          "algorithm": "SHA256",
          "checksumValue": "3698a2ac5c96ba514b28be021af6a08c41c55ad21af628f1dab8cf6b4eb4aaf4"
        },
        {
          "algorithm": "SHA512",
          "checksumValue": "14ae88bcf5b66f378ef08171dbabdc91b5166704ca17be8e47220b778b3b73d6fb0720ce70c5f605df845b1d4a00061abb6e200a9b63bf5f2dbbbf3773991355"
        },
        {
          "algorithm": "SHA1",
          "checksumValue": "5b34d194066cf4091b52efcddf5c45c2a2da1b96"
        }
      ]
    },
    {
      "SPDXID": "SPDXRef-File-tmp.CvHgx0WVyh-pkg-poiana-serviceC95factoryC95client.go",
      "fileName": "pkg/poiana/service_factory_client.go",
      "copyrightText": "NOASSERTION",
      "licenseConcluded": "Apache-2.0",
      "fileTypes": [
        "SOURCE"
      ],
      "licenseInfoInFiles": [
        "NONE"
      ],
      "checksums": [
        {
          "algorithm": "SHA512",
          "checksumValue": "fea19d35b1f5508c04bed0e9a7d0bee768045565da0582be33f77cd281aed487a574a553a8bb8191d73edf7bad5493bc938221c4d87c3530e0c28f7f54d696e6"
        },
        {
          "algorithm": "SHA1",
          "checksumValue": "993a1f1c8c8b84c985566c1813091f6ca6e5bb2f"
        },
        {
          "algorithm": "SHA256",
          "checksumValue": "d5a31fd3c27e2181af9196d0d7ba91a07de6f58793096cb379a1253f86f201c0"
        }
      ]
    },
    {
      "SPDXID": "SPDXRef-File-tmp.CvHgx0WVyh-go.sum",
      "fileName": "go.sum",
      "copyrightText": "NOASSERTION",
      "licenseConcluded": "Apache-2.0",
      "fileTypes": [
        "OTHER"
      ],
      "licenseInfoInFiles": [
        "NONE"
      ],
      "checksums": [
        {
          "algorithm": "SHA256",
          "checksumValue": "53f2f1da0d267c7bc17b775bc721eb07a58de9cd785807b6d063de57bacf1d92"
        },
        {
          "algorithm": "SHA512",
          "checksumValue": "9fc0ef209cc68e3078b54f4bc013f6538d8679fe809d7b90fe6fdb201b8c92aaf98086a0a79d5c52794f35dd63d6f806d0052939696de8dd93f7fb8f820cd7ea"
        },
        {
          "algorithm": "SHA1",
          "checksumValue": "7d84c39b19e788520b994dc4715af5c36c57cac8"
        }
      ]
    },
    {
      "SPDXID": "SPDXRef-File-tmp.CvHgx0WVyh-.github-workflows-release.yaml",
      "fileName": ".github/workflows/release.yaml",
      "copyrightText": "NOASSERTION",
      "licenseConcluded": "Apache-2.0",
      "fileTypes": [
        "TEXT"
      ],
      "licenseInfoInFiles": [
        "NONE"
      ],
      "checksums": [
        {
          "algorithm": "SHA1",
          "checksumValue": "579baf67aebb5cfe3b7ca436d17443ab71a07101"
        },
        {
          "algorithm": "SHA256",
          "checksumValue": "ba2b9bd84774edabd73922dc81b14ee014420798c01bdf0f59389a1a76298668"
        },
        {
          "algorithm": "SHA512",
          "checksumValue": "2430dafb3de70abb6415306ffc491f2884fdfbb319302bee6bdc77d96d5a81714ef3543c528c497ef8088ad5f2f14347cd660f8c9f46e3fbd3ea7e1696ea2b40"
        }
      ]
    },
    {
      "SPDXID": "SPDXRef-File-tmp.CvHgx0WVyh-pkg-poiana-serviceC95factory.go",
      "fileName": "pkg/poiana/service_factory.go",
      "copyrightText": "NOASSERTION",
      "licenseConcluded": "Apache-2.0",
      "fileTypes": [
        "SOURCE"
      ],
      "licenseInfoInFiles": [
        "NONE"
      ],
      "checksums": [
        {
          "algorithm": "SHA1",
          "checksumValue": "96eb1c6a62a784f821e06feaf25f9a9b8fd88e38"
        },
        {
          "algorithm": "SHA256",
          "checksumValue": "1818fc210b9a3b0ed620f0de3552e209d05b81109c133dec05d96c43d1db06ff"
        },
        {
          "algorithm": "SHA512",
          "checksumValue": "525d42b740cf984f54feaa080d84539a89ccd0788d64d4f35aef17d7060f1fffd2a21ac17495a47599a3a0ac30ef4d64057160e4ee915da59518cd3ae6191465"
        }
      ]
    },
    {
      "SPDXID": "SPDXRef-File-tmp.CvHgx0WVyh-README.md",
      "fileName": "README.md",
      "copyrightText": "NOASSERTION",
      "licenseConcluded": "Apache-2.0",
      "fileTypes": [
        "TEXT",
        "DOCUMENTATION"
      ],
      "licenseInfoInFiles": [
        "NONE"
      ],
      "checksums": [
        {
          "algorithm": "SHA512",
          "checksumValue": "b6de4877dd36a56726f714efa47599febd82ff31fef29258f3b682627d95747cc456959028d6f29ce84161683ea78d185e4367c73b296f9a232c18f982e522c1"
        },
        {
          "algorithm": "SHA1",
          "checksumValue": "92a269c7efb2aea884997cd3e7103ee63c0fb52a"
        },
        {
          "algorithm": "SHA256",
          "checksumValue": "5f3cab17a6e4eb92cd88a319d2f3f01156cea207bf6653dce89d51f60ee6decf"
        }
      ]
    },
    {
      "SPDXID": "SPDXRef-File-tmp.CvHgx0WVyh-pkg-poiana-variables.go",
      "fileName": "pkg/poiana/variables.go",
      "copyrightText": "NOASSERTION",
      "licenseConcluded": "Apache-2.0",
      "fileTypes": [
        "SOURCE"
      ],
      "licenseInfoInFiles": [
        "NONE"
      ],
      "checksums": [
        {
          "algorithm": "SHA1",
          "checksumValue": "407b86230f07627be1cf9b43e4e43c8db0432a7c"
        },
        {
          "algorithm": "SHA256",
          "checksumValue": "1e568bb577ef5000c98fc5c9a62defc28a1aa65f043e9cc0dc318809edd51de0"
        },
        {
          "algorithm": "SHA512",
          "checksumValue": "56a820b30999904cbddae24c90e592750474444fa36718a81f1b366db9c07244cc90bac46f1df6d1846e01c17281537f2a9dcd1cca6e827e7843f9698cebc6d2"
        }
      ]
    },
    {
      "SPDXID": "SPDXRef-File-tmp.CvHgx0WVyh-.github-PULLC95REQUESTC95TEMPLATE.md",
      "fileName": ".github/PULL_REQUEST_TEMPLATE.md",
      "copyrightText": "NOASSERTION",
      "licenseConcluded": "Apache-2.0",
      "fileTypes": [
        "TEXT",
        "DOCUMENTATION"
      ],
      "licenseInfoInFiles": [
        "NONE"
      ],
      "checksums": [
        {
          "algorithm": "SHA512",
          "checksumValue": "52d3519b82efe3e6fa9d51620f3236eb61c018774276cb042b45ed70aeae9b592ef131d2c3ea422839f4eaba66d8ef81bbf8aa2c734eeebed46bb0ea3bf3fd8c"
        },
        {
          "algorithm": "SHA1",
          "checksumValue": "d825aa5b92265259386230ec3ffb35a713aff089"
        },
        {
          "algorithm": "SHA256",
          "checksumValue": "1af7f3bde379c3bd477813e7ec3fba59c2946c2fb720af90a7cb97b1d8e58083"
        }
      ]
    },
    {
      "SPDXID": "SPDXRef-File-tmp.CvHgx0WVyh-pkg-poiana-secretsC95client.go",
      "fileName": "pkg/poiana/secrets_client.go",
      "copyrightText": "NOASSERTION",
      "licenseConcluded": "Apache-2.0",
      "fileTypes": [
        "SOURCE"
      ],
      "licenseInfoInFiles": [
        "NONE"
      ],
      "checksums": [
        {
          "algorithm": "SHA1",
          "checksumValue": "2f810f3f24eec05e956925204f5bc4625d28579b"
        },
        {
          "algorithm": "SHA256",
          "checksumValue": "954f7099f1dc3fa98ee982f8ccf9b7d0eaae1d68740e5614d1f7749b8ee9db44"
        },
        {
          "algorithm": "SHA512",
          "checksumValue": "cb2b2345d7a48e0017a8c4e537373a632dc478cf97d8d70e97cc1fa475b065eac00d0ba3a82ea5d6229af97854057377dec5341923412c34bb61390f463f7892"
        }
      ]
    },
    {
      "SPDXID": "SPDXRef-File-tmp.CvHgx0WVyh-pkg-poiana-variablesC95client.go",
      "fileName": "pkg/poiana/variables_client.go",
      "copyrightText": "NOASSERTION",
      "licenseConcluded": "Apache-2.0",
      "fileTypes": [
        "SOURCE"
      ],
      "licenseInfoInFiles": [
        "NONE"
      ],
      "checksums": [
        {
          "algorithm": "SHA1",
          "checksumValue": "321b676e395542a18345967dcaaeab51cf12abee"
        },
        {
          "algorithm": "SHA256",
          "checksumValue": "9fa367e7d4db48181164d31d72d9414425b29bae4d011f920349fc05034f8898"
        },
        {
          "algorithm": "SHA512",
          "checksumValue": "d23bfdfd3064f1e38abd8804c8d39a1f135f7dce57a3fa8612275d1307d34f62b3ce4e7ac85e102e42b9b48b464d420f94f1e1a0e03266fc2c08363c190311e0"
        }
      ]
    },
    {
      "SPDXID": "SPDXRef-File-tmp.CvHgx0WVyh-.gitignore",
      "fileName": ".gitignore",
      "copyrightText": "NOASSERTION",
      "licenseConcluded": "Apache-2.0",
      "fileTypes": [
        "OTHER"
      ],
      "licenseInfoInFiles": [
        "NONE"
      ],
      "checksums": [
        {
          "algorithm": "SHA256",
          "checksumValue": "8fadad94b4f568f9427bd9a4d5c2c2d7d44be5c466c950c94b803f5b66b6ed6c"
        },
        {
          "algorithm": "SHA512",
          "checksumValue": "0b62b1d6995c0b808c46c45c95a9c30818abf78a8becc202e623707fb7f4c7da6d495750f64319004cbf9abe41055771671af255e6f2bbe08b969ee5afa08973"
        },
        {
          "algorithm": "SHA1",
          "checksumValue": "054846c1b825d6a985094efd7c8e9af5893a17bc"
        }
      ]
    },
    {
      "SPDXID": "SPDXRef-File-tmp.CvHgx0WVyh-release.md",
      "fileName": "release.md",
      "copyrightText": "NOASSERTION",
      "licenseConcluded": "Apache-2.0",
      "fileTypes": [
        "TEXT",
        "DOCUMENTATION"
      ],
      "licenseInfoInFiles": [
        "NONE"
      ],
      "checksums": [
        {
          "algorithm": "SHA1",
          "checksumValue": "73e8f39ba5e49b79bc7e2bfafcd52999e1f84d92"
        },
        {
          "algorithm": "SHA256",
          "checksumValue": "14298f6530a7b5a57c2b230a26aa22caae69380406f7e49bda044409eb9c70cf"
        },
        {
          "algorithm": "SHA512",
          "checksumValue": "896838c89d593ffd3b70641c465099ca0d6787a9b86f8f2a71b735a795c92e1231a0c3fc47fe54f7f9b864238011b4c00ddda8476dce8a3c94a2ee5003def557"
        }
      ]
    },
    {
      "SPDXID": "SPDXRef-File-tmp.CvHgx0WVyh-pkg-poiana-variablesC95mock.go",
      "fileName": "pkg/poiana/variables_mock.go",
      "copyrightText": "NOASSERTION",
      "licenseConcluded": "Apache-2.0",
      "fileTypes": [
        "SOURCE"
      ],
      "licenseInfoInFiles": [
        "NONE"
      ],
      "checksums": [
        {
          "algorithm": "SHA256",
          "checksumValue": "f898a5a195a6cd12bfad0b99d88c757016d9c246dfe3c2de11d8dccd3477e32b"
        },
        {
          "algorithm": "SHA512",
          "checksumValue": "5a1e72a12bf4ca00b7371b2dcfcef201b09599944fbe8275a84798a3345cdfd508babc43c32f9bc61a203611a89a307b48d9a22703818cdb512b937c551d012f"
        },
        {
          "algorithm": "SHA1",
          "checksumValue": "20ff143c66298517c30fcf225042242213bc8086"
        }
      ]
    },
    {
      "SPDXID": "SPDXRef-File-tmp.CvHgx0WVyh-.github-workflows-ci.yaml",
      "fileName": ".github/workflows/ci.yaml",
      "copyrightText": "NOASSERTION",
      "licenseConcluded": "Apache-2.0",
      "fileTypes": [
        "TEXT"
      ],
      "licenseInfoInFiles": [
        "NONE"
      ],
      "checksums": [
        {
          "algorithm": "SHA256",
          "checksumValue": "67665af0f5b7c6319a525110308263be6bf0ce59efe7362fc7aab0311f2d238f"
        },
        {
          "algorithm": "SHA512",
          "checksumValue": "4883e263a5948ef0232c86a47ddfa9acf0953eac5e029d9f13ed6dfd343230782e00ae22344839159ed5929bad87932490ce18eb3cd5c2396d6cf4221af39dba"
        },
        {
          "algorithm": "SHA1",
          "checksumValue": "df006e87794062099eab16b99dae17e87574c243"
        }
      ]
    },
    {
      "SPDXID": "SPDXRef-File-tmp.CvHgx0WVyh-pkg-poiana-serviceC95factoryC95mock.go",
      "fileName": "pkg/poiana/service_factory_mock.go",
      "copyrightText": "NOASSERTION",
      "licenseConcluded": "Apache-2.0",
      "fileTypes": [
        "SOURCE"
      ],
      "licenseInfoInFiles": [
        "NONE"
      ],
      "checksums": [
        {
          "algorithm": "SHA256",
          "checksumValue": "b53aa3f6a1b8f618637a2e7866dc461c0fe1a5aad9fa62c350e3e8b7b65c609d"
        },
        {
          "algorithm": "SHA512",
          "checksumValue": "858f4d3a5034a2f400df849b7ec40b98c40e8c25ff8bce74ccfa77c67a94e2ca8e443e94b42ed9677cc044aebdc4d5c6cbb9ab63490596ad7697c0f5334ad537"
        },
        {
          "algorithm": "SHA1",
          "checksumValue": "ccdccab1ecd48a9c0500d12fa9f23bdc47f7d75b"
        }
      ]
    },
    {
      "SPDXID": "SPDXRef-File-tmp.CvHgx0WVyh-LICENSE",
      "fileName": "LICENSE",
      "copyrightText": "NOASSERTION",
      "licenseConcluded": "Apache-2.0",
      "fileTypes": [
        "TEXT",
        "DOCUMENTATION"
      ],
      "licenseInfoInFiles": [
        "Apache-2.0"
      ],
      "checksums": [
        {
          "algorithm": "SHA1",
          "checksumValue": "eb813b8fdb2276a4454e99623a7eee9507f7fc77"
        },
        {
          "algorithm": "SHA256",
          "checksumValue": "21ec9433a87459b3477faf542bacec419dc03af841309eac35edeffe481cf10b"
        },
        {
          "algorithm": "SHA512",
          "checksumValue": "cf5d262179624006fdca082d832fe67da1d6b549efdc7a4526553b4008bbee1b2d7d570d42e3d24e0101962ec3cb6fdccb22cbf4fe158e2fcf59b950fe61a794"
        }
      ]
    },
    {
      "SPDXID": "SPDXRef-File-tmp.CvHgx0WVyh-pkg-poiana-secretsC95mock.go",
      "fileName": "pkg/poiana/secrets_mock.go",
      "copyrightText": "NOASSERTION",
      "licenseConcluded": "Apache-2.0",
      "fileTypes": [
        "SOURCE"
      ],
      "licenseInfoInFiles": [
        "NONE"
      ],
      "checksums": [
        {
          "algorithm": "SHA256",
          "checksumValue": "54a7f87b77ce7121e000828ce8b4e8296b0a03e6265e3f88b471faad9bf17ec7"
        },
        {
          "algorithm": "SHA512",
          "checksumValue": "2999157e5d597a4eaac9c11c6ce73bc4c1c5f359e4c17c6d1e46464b674c6f1c7a5a9c6ee45bba411601e6fb0c9e488b7a1579621e1cd885bfc378c116448e20"
        },
        {
          "algorithm": "SHA1",
          "checksumValue": "4b27eeca2f505f7c71acb454c13f9c4f09a9c433"
        }
      ]
    },
    {
      "SPDXID": "SPDXRef-File-tmp.CvHgx0WVyh-pkg-config-config.go",
      "fileName": "pkg/config/config.go",
      "copyrightText": "NOASSERTION",
      "licenseConcluded": "Apache-2.0",
      "fileTypes": [
        "SOURCE"
      ],
      "licenseInfoInFiles": [
        "NONE"
      ],
      "checksums": [
        {
          "algorithm": "SHA1",
          "checksumValue": "992891ba908bea225e208ebad960067fd7afb0a6"
        },
        {
          "algorithm": "SHA256",
          "checksumValue": "c535c6861ae604a32b7b10536161bf151c4c65ee1227d55078c81040546f0e3d"
        },
        {
          "algorithm": "SHA512",
          "checksumValue": "e0e006a1b73dd025790535b61b6fdd0e46bbcf32eba75bf8e48784be97f7f1640e4a1e0e07dc362f5d343f99e3d3f6dbb3786bd7cc5a14e2edeef341445ecd2a"
        }
      ]
    },
    {
      "SPDXID": "SPDXRef-File-tmp.CvHgx0WVyh-go.mod",
      "fileName": "go.mod",
      "copyrightText": "NOASSERTION",
      "licenseConcluded": "Apache-2.0",
      "fileTypes": [
        "OTHER"
      ],
      "licenseInfoInFiles": [
        "NONE"
      ],
      "checksums": [
        {
          "algorithm": "SHA1",
          "checksumValue": "47b77e12573ffd07b3bf5a2fa534bfdbeb703c7e"
        },
        {
          "algorithm": "SHA256",
          "checksumValue": "2c82bd6062f848319f33934885417b2b3d0421af6dd9c65d1a6c4ca41c86b3f3"
        },
        {
          "algorithm": "SHA512",
          "checksumValue": "a6d016de1785702c601feff7dfcc96fa63b47e5040fbe5f13bb011f039699d3a8bf675a4b778833d278287f320e8c6549e0224b09beaed43ffed90a30695d7c5"
        }
      ]
    },
    {
      "SPDXID": "SPDXRef-File-tmp.CvHgx0WVyh-pkg-poiana-secretsC95onepassword.go",
      "fileName": "pkg/poiana/secrets_onepassword.go",
      "copyrightText": "NOASSERTION",
      "licenseConcluded": "Apache-2.0",
      "fileTypes": [
        "SOURCE"
      ],
      "licenseInfoInFiles": [
        "NONE"
      ],
      "checksums": [
        {
          "algorithm": "SHA1",
          "checksumValue": "66fcf111b1552ae7f2a7814553cf52c3df6917fb"
        },
        {
          "algorithm": "SHA256",
          "checksumValue": "5a135c49ba0a3c05a93be2b7266cac87cdac76b7d212d929807a996220031411"
        },
        {
          "algorithm": "SHA512",
          "checksumValue": "60bf09236bfaf62a745b65e908b4910425ed88a10580bf326e7e90a9143b957ba79d3d5980196d989332cd4633592ea694daa927e568f14310987a8d1ad6d1cb"
        }
      ]
    },
    {
      "SPDXID": "SPDXRef-File-tmp.CvHgx0WVyh-Makefile",
      "fileName": "Makefile",
      "copyrightText": "NOASSERTION",
      "licenseConcluded": "Apache-2.0",
      "fileTypes": [
        "BINARY",
        "APPLICATION"
      ],
      "licenseInfoInFiles": [
        "NONE"
      ],
      "checksums": [
        {
          "algorithm": "SHA1",
          "checksumValue": "c588953134b331ab9f73dad440877bd9869f7628"
        },
        {
          "algorithm": "SHA256",
          "checksumValue": "4dd8f0b651836a782c6dc63d9d634da82f33048ded1a5febfb857d286243f281"
        },
        {
          "algorithm": "SHA512",
          "checksumValue": "32014a06396729533cdb88685d8bd756639c1a7ecd408a9424a12f0052681e1060165ad3d15fad06e92723aaf7f009dfd5356feb03c9e3a39e2d18b730d32523"
        }
      ]
    },
    {
      "SPDXID": "SPDXRef-File-tmp.CvHgx0WVyh-OWNERS",
      "fileName": "OWNERS",
      "copyrightText": "NOASSERTION",
      "licenseConcluded": "Apache-2.0",
      "fileTypes": [
        "BINARY",
        "APPLICATION"
      ],
      "licenseInfoInFiles": [
        "NONE"
      ],
      "checksums": [
        {
          "algorithm": "SHA512",
          "checksumValue": "d71b9574aa07830d090407cbc95774760d925c915741b1192d637381d6c5aae3602741e47bff19e318fe0ce124e2bbc1eaeeb31b8d68477194d9e7019eaa4771"
        },
        {
          "algorithm": "SHA1",
          "checksumValue": "d8bcfd1d6a21304aeea4912510de1e97f00ac9df"
        },
        {
          "algorithm": "SHA256",
          "checksumValue": "a927828e6460d63912c9c9cfb810b10be08b40ef9be4b016ff83d82e5c5e5d9c"
        }
      ]
    },
    {
      "SPDXID": "SPDXRef-File-tmp.CvHgx0WVyh-main.go",
      "fileName": "main.go",
      "copyrightText": "NOASSERTION",
      "licenseConcluded": "Apache-2.0",
      "fileTypes": [
        "SOURCE"
      ],
      "licenseInfoInFiles": [
        "NONE"
      ],
      "checksums": [
        {
          "algorithm": "SHA512",
          "checksumValue": "ebced9bc1bfe550314ea0c7134d1e30bb5fbec8c04e9cdc2a0003a86edceadfcd26244a21b61a418f61d030610f7577297689949a76de83b3ceeb7f8c5a27626"
        },
        {
          "algorithm": "SHA1",
          "checksumValue": "6a0db5ced7e521d98053fc407d09558df91fc4cf"
        },
        {
          "algorithm": "SHA256",
          "checksumValue": "4b627b8006ae1531b8fad58b09a49cce4d667aacdece82dbb7a4dd02cba0711c"
        }
      ]
    },
    {
      "SPDXID": "SPDXRef-File-tmp.CvHgx0WVyh-.goreleaser.yml",
      "fileName": ".goreleaser.yml",
      "copyrightText": "NOASSERTION",
      "licenseConcluded": "Apache-2.0",
      "fileTypes": [
        "TEXT"
      ],
      "licenseInfoInFiles": [
        "NONE"
      ],
      "checksums": [
        {
          "algorithm": "SHA1",
          "checksumValue": "3b636f0c39b6ea59edc59cf67ff50d31019b6e5e"
        },
        {
          "algorithm": "SHA256",
          "checksumValue": "146045e5d2c4171ccd94b4ebf58481831808bf0f9024f3d1260b8052d05c3938"
        },
        {
          "algorithm": "SHA512",
          "checksumValue": "882d32c3467249be9c10bd4f20f129333457621059db6378050aa93129ecb3e1fd4a0462d635250500d110835e6013dfca0ded9c949e8e455390b947022eb97a"
        }
      ]
    }
  ],
  "packages": [
    {
      "SPDXID": "SPDXRef-Package-gomod-github.com-1Password-connect-sdk-go-v1.5.0",
      "name": "github.com/1Password/connect-sdk-go",
      "versionInfo": "v1.5.0",
      "filesAnalyzed": false,
      "licenseConcluded": "MIT",
      "downloadLocation": "https://proxy.golang.org/github.com/1Password/connect-sdk-go/@v/v1.5.0.zip",
      "copyrightText": "MIT License\n\nCopyright (c) 2021 1Password\n\nPermission is hereby granted, free of charge, to any person obtaining a copy\nof this software and associated documentation files (the \"Software\"), to deal\nin the Software without restriction, including without limitation the rights\nto use, copy, modify, merge, publish, distribute, sublicense, and/or sell\ncopies of the Software, and to permit persons to whom the Software is\nfurnished to do so, subject to the following conditions:\n\nThe above copyright notice and this permission notice shall be included in all\ncopies or substantial portions of the Software.\n\nTHE SOFTWARE IS PROVIDED \"AS IS\", WITHOUT WARRANTY OF ANY KIND, EXPRESS OR\nIMPLIED, INCLUDING BUT NOT LIMITED TO THE WARRANTIES OF MERCHANTABILITY,\nFITNESS FOR A PARTICULAR PURPOSE AND NONINFRINGEMENT. IN NO EVENT SHALL THE\nAUTHORS OR COPYRIGHT HOLDERS BE LIABLE FOR ANY CLAIM, DAMAGES OR OTHER\nLIABILITY, WHETHER IN AN ACTION OF CONTRACT, TORT OR OTHERWISE, ARISING FROM,\nOUT OF OR IN CONNECTION WITH THE SOFTWARE OR THE USE OR OTHER DEALINGS IN THE\nSOFTWARE.\n",
      "checksums": [],
      "externalRefs": [
        {
          "referenceCategory": "PACKAGE-MANAGER",
          "referenceLocator": "pkg:golang/github.com/1Password/connect-sdk-go@v1.5.0",
          "referenceType": "purl"
        }
      ]
    },
    {
      "SPDXID": "SPDXRef-Package-gomod-golang.org-x-net-v0.0.0-20210226172049-e18ecbb05110",
      "name": "golang.org/x/net",
      "versionInfo": "v0.0.0-20210226172049-e18ecbb05110",
      "filesAnalyzed": false,
      "licenseConcluded": "BSD-3-Clause",
      "downloadLocation": "https://proxy.golang.org/golang.org/x/net/@v/v0.0.0-20210226172049-e18ecbb05110.zip",
      "copyrightText": "Copyright (c) 2009 The Go Authors. All rights reserved.\n\nRedistribution and use in source and binary forms, with or without\nmodification, are permitted provided that the following conditions are\nmet:\n\n   * Redistributions of source code must retain the above copyright\nnotice, this list of conditions and the following disclaimer.\n   * Redistributions in binary form must reproduce the above\ncopyright notice, this list of conditions and the following disclaimer\nin the documentation and/or other materials provided with the\ndistribution.\n   * Neither the name of Google Inc. nor the names of its\ncontributors may be used to endorse or promote products derived from\nthis software without specific prior written permission.\n\nTHIS SOFTWARE IS PROVIDED BY THE COPYRIGHT HOLDERS AND CONTRIBUTORS\n\"AS IS\" AND ANY EXPRESS OR IMPLIED WARRANTIES, INCLUDING, BUT NOT\nLIMITED TO, THE IMPLIED WARRANTIES OF MERCHANTABILITY AND FITNESS FOR\nA PARTICULAR PURPOSE ARE DISCLAIMED. IN NO EVENT SHALL THE COPYRIGHT\nOWNER OR CONTRIBUTORS BE LIABLE FOR ANY DIRECT, INDIRECT, INCIDENTAL,\nSPECIAL, EXEMPLARY, OR CONSEQUENTIAL DAMAGES (INCLUDING, BUT NOT\nLIMITED TO, PROCUREMENT OF SUBSTITUTE GOODS OR SERVICES; LOSS OF USE,\nDATA, OR PROFITS; OR BUSINESS INTERRUPTION) HOWEVER CAUSED AND ON ANY\nTHEORY OF LIABILITY, WHETHER IN CONTRACT, STRICT LIABILITY, OR TORT\n(INCLUDING NEGLIGENCE OR OTHERWISE) ARISING IN ANY WAY OUT OF THE USE\nOF THIS SOFTWARE, EVEN IF ADVISED OF THE POSSIBILITY OF SUCH DAMAGE.\n",
      "checksums": [],
      "externalRefs": [
        {
          "referenceCategory": "PACKAGE-MANAGER",
          "referenceLocator": "pkg:golang/golang.org/x/net@v0.0.0-20210226172049-e18ecbb05110",
          "referenceType": "purl"
        }
      ]
    },
    {
      "SPDXID": "SPDXRef-Package-gomod-github.com-sirupsen-logrus-v1.9.0",
      "name": "github.com/sirupsen/logrus",
      "versionInfo": "v1.9.0",
      "filesAnalyzed": false,
      "licenseConcluded": "MIT",
      "downloadLocation": "https://proxy.golang.org/github.com/sirupsen/logrus/@v/v1.9.0.zip",
      "copyrightText": "The MIT License (MIT)\n\nCopyright (c) 2014 Simon Eskildsen\n\nPermission is hereby granted, free of charge, to any person obtaining a copy\nof this software and associated documentation files (the \"Software\"), to deal\nin the Software without restriction, including without limitation the rights\nto use, copy, modify, merge, publish, distribute, sublicense, and/or sell\ncopies of the Software, and to permit persons to whom the Software is\nfurnished to do so, subject to the following conditions:\n\nThe above copyright notice and this permission notice shall be included in\nall copies or substantial portions of the Software.\n\nTHE SOFTWARE IS PROVIDED \"AS IS\", WITHOUT WARRANTY OF ANY KIND, EXPRESS OR\nIMPLIED, INCLUDING BUT NOT LIMITED TO THE WARRANTIES OF MERCHANTABILITY,\nFITNESS FOR A PARTICULAR PURPOSE AND NONINFRINGEMENT. IN NO EVENT SHALL THE\nAUTHORS OR COPYRIGHT HOLDERS BE LIABLE FOR ANY CLAIM, DAMAGES OR OTHER\nLIABILITY, WHETHER IN AN ACTION OF CONTRACT, TORT OR OTHERWISE, ARISING FROM,\nOUT OF OR IN CONNECTION WITH THE SOFTWARE OR THE USE OR OTHER DEALINGS IN\nTHE SOFTWARE.\n",
      "checksums": [],
      "externalRefs": [
        {
          "referenceCategory": "PACKAGE-MANAGER",
          "referenceLocator": "pkg:golang/github.com/sirupsen/logrus@v1.9.0",
          "referenceType": "purl"
        }
      ]
    },
    {
      "SPDXID": "SPDXRef-Package-gomod-golang.org-x-sys-v0.0.0-20220715151400-c0bba94af5f8",
      "name": "golang.org/x/sys",
      "versionInfo": "v0.0.0-20220715151400-c0bba94af5f8",
      "filesAnalyzed": false,
      "licenseConcluded": "BSD-3-Clause",
      "downloadLocation": "https://proxy.golang.org/golang.org/x/sys/@v/v0.0.0-20220715151400-c0bba94af5f8.zip",
      "copyrightText": "Copyright (c) 2009 The Go Authors. All rights reserved.\n\nRedistribution and use in source and binary forms, with or without\nmodification, are permitted provided that the following conditions are\nmet:\n\n   * Redistributions of source code must retain the above copyright\nnotice, this list of conditions and the following disclaimer.\n   * Redistributions in binary form must reproduce the above\ncopyright notice, this list of conditions and the following disclaimer\nin the documentation and/or other materials provided with the\ndistribution.\n   * Neither the name of Google Inc. nor the names of its\ncontributors may be used to endorse or promote products derived from\nthis software without specific prior written permission.\n\nTHIS SOFTWARE IS PROVIDED BY THE COPYRIGHT HOLDERS AND CONTRIBUTORS\n\"AS IS\" AND ANY EXPRESS OR IMPLIED WARRANTIES, INCLUDING, BUT NOT\nLIMITED TO, THE IMPLIED WARRANTIES OF MERCHANTABILITY AND FITNESS FOR\nA PARTICULAR PURPOSE ARE DISCLAIMED. IN NO EVENT SHALL THE COPYRIGHT\nOWNER OR CONTRIBUTORS BE LIABLE FOR ANY DIRECT, INDIRECT, INCIDENTAL,\nSPECIAL, EXEMPLARY, OR CONSEQUENTIAL DAMAGES (INCLUDING, BUT NOT\nLIMITED TO, PROCUREMENT OF SUBSTITUTE GOODS OR SERVICES; LOSS OF USE,\nDATA, OR PROFITS; OR BUSINESS INTERRUPTION) HOWEVER CAUSED AND ON ANY\nTHEORY OF LIABILITY, WHETHER IN CONTRACT, STRICT LIABILITY, OR TORT\n(INCLUDING NEGLIGENCE OR OTHERWISE) ARISING IN ANY WAY OUT OF THE USE\nOF THIS SOFTWARE, EVEN IF ADVISED OF THE POSSIBILITY OF SUCH DAMAGE.\n",
      "checksums": [],
      "externalRefs": [
        {
          "referenceCategory": "PACKAGE-MANAGER",
          "referenceLocator": "pkg:golang/golang.org/x/sys@v0.0.0-20220715151400-c0bba94af5f8",
          "referenceType": "purl"
        }
      ]
    },
    {
      "SPDXID": "SPDXRef-Package-gomod-github.com-opentracing-opentracing-go-v1.2.0",
      "name": "github.com/opentracing/opentracing-go",
      "versionInfo": "v1.2.0",
      "filesAnalyzed": false,
      "licenseConcluded": "Apache-2.0",
      "downloadLocation": "https://proxy.golang.org/github.com/opentracing/opentracing-go/@v/v1.2.0.zip",
      "copyrightText": "                                 Apache License\n                           Version 2.0, January 2004\n                        http://www.apache.org/licenses/\n\n   TERMS AND CONDITIONS FOR USE, REPRODUCTION, AND DISTRIBUTION\n\n   1. Definitions.\n\n      \"License\" shall mean the terms and conditions for use, reproduction,\n      and distribution as defined by Sections 1 through 9 of this document.\n\n      \"Licensor\" shall mean the copyright owner or entity authorized by\n      the copyright owner that is granting the License.\n\n      \"Legal Entity\" shall mean the union of the acting entity and all\n      other entities that control, are controlled by, or are under common\n      control with that entity. For the purposes of this definition,\n      \"control\" means (i) the power, direct or indirect, to cause the\n      direction or management of such entity, whether by contract or\n      otherwise, or (ii) ownership of fifty percent (50%) or more of the\n      outstanding shares, or (iii) beneficial ownership of such entity.\n\n      \"You\" (or \"Your\") shall mean an individual or Legal Entity\n      exercising permissions granted by this License.\n\n      \"Source\" form shall mean the preferred form for making modifications,\n      including but not limited to software source code, documentation\n      source, and configuration files.\n\n      \"Object\" form shall mean any form resulting from mechanical\n      transformation or translation of a Source form, including but\n      not limited to compiled object code, generated documentation,\n      and conversions to other media types.\n\n      \"Work\" shall mean the work of authorship, whether in Source or\n      Object form, made available under the License, as indicated by a\n      copyright notice that is included in or attached to the work\n      (an example is provided in the Appendix below).\n\n      \"Derivative Works\" shall mean any work, whether in Source or Object\n      form, that is based on (or derived from) the Work and for which the\n      editorial revisions, annotations, elaborations, or other modifications\n      represent, as a whole, an original work of authorship. For the purposes\n      of this License, Derivative Works shall not include works that remain\n      separable from, or merely link (or bind by name) to the interfaces of,\n      the Work and Derivative Works thereof.\n\n      \"Contribution\" shall mean any work of authorship, including\n      the original version of the Work and any modifications or additions\n      to that Work or Derivative Works thereof, that is intentionally\n      submitted to Licensor for inclusion in the Work by the copyright owner\n      or by an individual or Legal Entity authorized to submit on behalf of\n      the copyright owner. For the purposes of this definition, \"submitted\"\n      means any form of electronic, verbal, or written communication sent\n      to the Licensor or its representatives, including but not limited to\n      communication on electronic mailing lists, source code control systems,\n      and issue tracking systems that are managed by, or on behalf of, the\n      Licensor for the purpose of discussing and improving the Work, but\n      excluding communication that is conspicuously marked or otherwise\n      designated in writing by the copyright owner as \"Not a Contribution.\"\n\n      \"Contributor\" shall mean Licensor and any individual or Legal Entity\n      on behalf of whom a Contribution has been received by Licensor and\n      subsequently incorporated within the Work.\n\n   2. Grant of Copyright License. Subject to the terms and conditions of\n      this License, each Contributor hereby grants to You a perpetual,\n      worldwide, non-exclusive, no-charge, royalty-free, irrevocable\n      copyright license to reproduce, prepare Derivative Works of,\n      publicly display, publicly perform, sublicense, and distribute the\n      Work and such Derivative Works in Source or Object form.\n\n   3. Grant of Patent License. Subject to the terms and conditions of\n      this License, each Contributor hereby grants to You a perpetual,\n      worldwide, non-exclusive, no-charge, royalty-free, irrevocable\n      (except as stated in this section) patent license to make, have made,\n      use, offer to sell, sell, import, and otherwise transfer the Work,\n      where such license applies only to those patent claims licensable\n      by such Contributor that are necessarily infringed by their\n      Contribution(s) alone or by combination of their Contribution(s)\n      with the Work to which such Contribution(s) was submitted. If You\n      institute patent litigation against any entity (including a\n      cross-claim or counterclaim in a lawsuit) alleging that the Work\n      or a Contribution incorporated within the Work constitutes direct\n      or contributory patent infringement, then any patent licenses\n      granted to You under this License for that Work shall terminate\n      as of the date such litigation is filed.\n\n   4. Redistribution. You may reproduce and distribute copies of the\n      Work or Derivative Works thereof in any medium, with or without\n      modifications, and in Source or Object form, provided that You\n      meet the following conditions:\n\n      (a) You must give any other recipients of the Work or\n          Derivative Works a copy of this License; and\n\n      (b) You must cause any modified files to carry prominent notices\n          stating that You changed the files; and\n\n      (c) You must retain, in the Source form of any Derivative Works\n          that You distribute, all copyright, patent, trademark, and\n          attribution notices from the Source form of the Work,\n          excluding those notices that do not pertain to any part of\n          the Derivative Works; and\n\n      (d) If the Work includes a \"NOTICE\" text file as part of its\n          distribution, then any Derivative Works that You distribute must\n          include a readable copy of the attribution notices contained\n          within such NOTICE file, excluding those notices that do not\n          pertain to any part of the Derivative Works, in at least one\n          of the following places: within a NOTICE text file distributed\n          as part of the Derivative Works; within the Source form or\n          documentation, if provided along with the Derivative Works; or,\n          within a display generated by the Derivative Works, if and\n          wherever such third-party notices normally appear. The contents\n          of the NOTICE file are for informational purposes only and\n          do not modify the License. You may add Your own attribution\n          notices within Derivative Works that You distribute, alongside\n          or as an addendum to the NOTICE text from the Work, provided\n          that such additional attribution notices cannot be construed\n          as modifying the License.\n\n      You may add Your own copyright statement to Your modifications and\n      may provide additional or different license terms and conditions\n      for use, reproduction, or distribution of Your modifications, or\n      for any such Derivative Works as a whole, provided Your use,\n      reproduction, and distribution of the Work otherwise complies with\n      the conditions stated in this License.\n\n   5. Submission of Contributions. Unless You explicitly state otherwise,\n      any Contribution intentionally submitted for inclusion in the Work\n      by You to the Licensor shall be under the terms and conditions of\n      this License, without any additional terms or conditions.\n      Notwithstanding the above, nothing herein shall supersede or modify\n      the terms of any separate license agreement you may have executed\n      with Licensor regarding such Contributions.\n\n   6. Trademarks. This License does not grant permission to use the trade\n      names, trademarks, service marks, or product names of the Licensor,\n      except as required for reasonable and customary use in describing the\n      origin of the Work and reproducing the content of the NOTICE file.\n\n   7. Disclaimer of Warranty. Unless required by applicable law or\n      agreed to in writing, Licensor provides the Work (and each\n      Contributor provides its Contributions) on an \"AS IS\" BASIS,\n      WITHOUT WARRANTIES OR CONDITIONS OF ANY KIND, either express or\n      implied, including, without limitation, any warranties or conditions\n      of TITLE, NON-INFRINGEMENT, MERCHANTABILITY, or FITNESS FOR A\n      PARTICULAR PURPOSE. You are solely responsible for determining the\n      appropriateness of using or redistributing the Work and assume any\n      risks associated with Your exercise of permissions under this License.\n\n   8. Limitation of Liability. In no event and under no legal theory,\n      whether in tort (including negligence), contract, or otherwise,\n      unless required by applicable law (such as deliberate and grossly\n      negligent acts) or agreed to in writing, shall any Contributor be\n      liable to You for damages, including any direct, indirect, special,\n      incidental, or consequential damages of any character arising as a\n      result of this License or out of the use or inability to use the\n      Work (including but not limited to damages for loss of goodwill,\n      work stoppage, computer failure or malfunction, or any and all\n      other commercial damages or losses), even if such Contributor\n      has been advised of the possibility of such damages.\n\n   9. Accepting Warranty or Additional Liability. While redistributing\n      the Work or Derivative Works thereof, You may choose to offer,\n      and charge a fee for, acceptance of support, warranty, indemnity,\n      or other liability obligations and/or rights consistent with this\n      License. However, in accepting such obligations, You may act only\n      on Your own behalf and on Your sole responsibility, not on behalf\n      of any other Contributor, and only if You agree to indemnify,\n      defend, and hold each Contributor harmless for any liability\n      incurred by, or claims asserted against, such Contributor by reason\n      of your accepting any such warranty or additional liability.\n\n   END OF TERMS AND CONDITIONS\n\n   APPENDIX: How to apply the Apache License to your work.\n\n      To apply the Apache License to your work, attach the following\n      boilerplate notice, with the fields enclosed by brackets \"{}\"\n      replaced with your own identifying information. (Don't include\n      the brackets!)  The text should be enclosed in the appropriate\n      comment syntax for the file format. We also recommend that a\n      file or class name and description of purpose be included on the\n      same \"printed page\" as the copyright notice for easier\n      identification within third-party archives.\n\n   Copyright 2016 The OpenTracing Authors\n\n   Licensed under the Apache License, Version 2.0 (the \"License\");\n   you may not use this file except in compliance with the License.\n   You may obtain a copy of the License at\n\n       http://www.apache.org/licenses/LICENSE-2.0\n\n   Unless required by applicable law or agreed to in writing, software\n   distributed under the License is distributed on an \"AS IS\" BASIS,\n   WITHOUT WARRANTIES OR CONDITIONS OF ANY KIND, either express or implied.\n   See the License for the specific language governing permissions and\n   limitations under the License.\n",
      "checksums": [],
      "externalRefs": [
        {
          "referenceCategory": "PACKAGE-MANAGER",
          "referenceLocator": "pkg:golang/github.com/opentracing/opentracing-go@v1.2.0",
          "referenceType": "purl"
        }
      ]
    },
    {
      "SPDXID": "SPDXRef-Package-gomod-github.com-google-go-querystring-v1.1.0",
      "name": "github.com/google/go-querystring",
      "versionInfo": "v1.1.0",
      "filesAnalyzed": false,
      "licenseConcluded": "BSD-3-Clause",
      "downloadLocation": "https://proxy.golang.org/github.com/google/go-querystring/@v/v1.1.0.zip",
      "copyrightText": "Copyright (c) 2013 Google. All rights reserved.\n\nRedistribution and use in source and binary forms, with or without\nmodification, are permitted provided that the following conditions are\nmet:\n\n   * Redistributions of source code must retain the above copyright\nnotice, this list of conditions and the following disclaimer.\n   * Redistributions in binary form must reproduce the above\ncopyright notice, this list of conditions and the following disclaimer\nin the documentation and/or other materials provided with the\ndistribution.\n   * Neither the name of Google Inc. nor the names of its\ncontributors may be used to endorse or promote products derived from\nthis software without specific prior written permission.\n\nTHIS SOFTWARE IS PROVIDED BY THE COPYRIGHT HOLDERS AND CONTRIBUTORS\n\"AS IS\" AND ANY EXPRESS OR IMPLIED WARRANTIES, INCLUDING, BUT NOT\nLIMITED TO, THE IMPLIED WARRANTIES OF MERCHANTABILITY AND FITNESS FOR\nA PARTICULAR PURPOSE ARE DISCLAIMED. IN NO EVENT SHALL THE COPYRIGHT\nOWNER OR CONTRIBUTORS BE LIABLE FOR ANY DIRECT, INDIRECT, INCIDENTAL,\nSPECIAL, EXEMPLARY, OR CONSEQUENTIAL DAMAGES (INCLUDING, BUT NOT\nLIMITED TO, PROCUREMENT OF SUBSTITUTE GOODS OR SERVICES; LOSS OF USE,\nDATA, OR PROFITS; OR BUSINESS INTERRUPTION) HOWEVER CAUSED AND ON ANY\nTHEORY OF LIABILITY, WHETHER IN CONTRACT, STRICT LIABILITY, OR TORT\n(INCLUDING NEGLIGENCE OR OTHERWISE) ARISING IN ANY WAY OUT OF THE USE\nOF THIS SOFTWARE, EVEN IF ADVISED OF THE POSSIBILITY OF SUCH DAMAGE.\n",
      "checksums": [],
      "externalRefs": [
        {
          "referenceCategory": "PACKAGE-MANAGER",
          "referenceLocator": "pkg:golang/github.com/google/go-querystring@v1.1.0",
          "referenceType": "purl"
        }
      ]
    },
    {
      "SPDXID": "SPDXRef-Package-tmp.CvHgx0WVyh",
      "name": "tmp.CvHgx0WVyh",
      "versionInfo": "",
      "filesAnalyzed": true,
      "licenseConcluded": "Apache-2.0",
      "downloadLocation": "NONE",
      "copyrightText": "NOASSERTION",
      "hasFiles": [
        "SPDXRef-File-tmp.CvHgx0WVyh-.gitignore",
        "SPDXRef-File-tmp.CvHgx0WVyh-.github-workflows-release.yaml",
        "SPDXRef-File-tmp.CvHgx0WVyh-.github-workflows-ci.yaml",
        "SPDXRef-File-tmp.CvHgx0WVyh-.goreleaser.yml",
        "SPDXRef-File-tmp.CvHgx0WVyh-OWNERS",
        "SPDXRef-File-tmp.CvHgx0WVyh-Makefile",
        "SPDXRef-File-tmp.CvHgx0WVyh-README.md",
        "SPDXRef-File-tmp.CvHgx0WVyh-go.mod",
        "SPDXRef-File-tmp.CvHgx0WVyh-go.sum",
        "SPDXRef-File-tmp.CvHgx0WVyh-LICENSE",
        "SPDXRef-File-tmp.CvHgx0WVyh-main.go",
        "SPDXRef-File-tmp.CvHgx0WVyh-pkg-config-config.go",
        "SPDXRef-File-tmp.CvHgx0WVyh-pkg-poiana-secrets.go",
        "SPDXRef-File-tmp.CvHgx0WVyh-.github-PULLC95REQUESTC95TEMPLATE.md",
        "SPDXRef-File-tmp.CvHgx0WVyh-pkg-poiana-secretsC95client.go",
        "SPDXRef-File-tmp.CvHgx0WVyh-pkg-poiana-serviceC95factory.go",
        "SPDXRef-File-tmp.CvHgx0WVyh-pkg-poiana-secretsC95mock.go",
        "SPDXRef-File-tmp.CvHgx0WVyh-pkg-poiana-secretsC95onepassword.go",
        "SPDXRef-File-tmp.CvHgx0WVyh-pkg-config-configC95test.go",
        "SPDXRef-File-tmp.CvHgx0WVyh-pkg-poiana-serviceC95factoryC95mock.go",
        "SPDXRef-File-tmp.CvHgx0WVyh-pkg-poiana-variables.go",
        "SPDXRef-File-tmp.CvHgx0WVyh-pkg-poiana-variablesC95mock.go",
        "SPDXRef-File-tmp.CvHgx0WVyh-pkg-poiana-variablesC95client.go",
        "SPDXRef-File-tmp.CvHgx0WVyh-release.md",
        "SPDXRef-File-tmp.CvHgx0WVyh-pkg-poiana-serviceC95factoryC95client.go"
      ],
      "licenseInfoFromFiles": [
        "Apache-2.0"
      ],
      "checksums": [],
      "packageVerificationCode": {
        "packageVerificationCodeValue": "c3bd599db96e343662aef89ed8bf09f5eab28c8b"
      }
    },
    {
      "SPDXID": "SPDXRef-Package-gomod-gopkg.in-yaml.v3-v3.0.1",
      "name": "gopkg.in/yaml.v3",
      "versionInfo": "v3.0.1",
      "filesAnalyzed": false,
      "licenseConcluded": "MIT",
      "downloadLocation": "https://proxy.golang.org/gopkg.in/yaml.v3/@v/v3.0.1.zip",
      "copyrightText": "\nThis project is covered by two different licenses: MIT and Apache.\n\n#### MIT License ####\n\nThe following files were ported to Go from C files of libyaml, and thus\nare still covered by their original MIT license, with the additional\ncopyright staring in 2011 when the project was ported over:\n\n    apic.go emitterc.go parserc.go readerc.go scannerc.go\n    writerc.go yamlh.go yamlprivateh.go\n\nCopyright (c) 2006-2010 Kirill Simonov\nCopyright (c) 2006-2011 Kirill Simonov\n\nPermission is hereby granted, free of charge, to any person obtaining a copy of\nthis software and associated documentation files (the \"Software\"), to deal in\nthe Software without restriction, including without limitation the rights to\nuse, copy, modify, merge, publish, distribute, sublicense, and/or sell copies\nof the Software, and to permit persons to whom the Software is furnished to do\nso, subject to the following conditions:\n\nThe above copyright notice and this permission notice shall be included in all\ncopies or substantial portions of the Software.\n\nTHE SOFTWARE IS PROVIDED \"AS IS\", WITHOUT WARRANTY OF ANY KIND, EXPRESS OR\nIMPLIED, INCLUDING BUT NOT LIMITED TO THE WARRANTIES OF MERCHANTABILITY,\nFITNESS FOR A PARTICULAR PURPOSE AND NONINFRINGEMENT. IN NO EVENT SHALL THE\nAUTHORS OR COPYRIGHT HOLDERS BE LIABLE FOR ANY CLAIM, DAMAGES OR OTHER\nLIABILITY, WHETHER IN AN ACTION OF CONTRACT, TORT OR OTHERWISE, ARISING FROM,\nOUT OF OR IN CONNECTION WITH THE SOFTWARE OR THE USE OR OTHER DEALINGS IN THE\nSOFTWARE.\n\n### Apache License ###\n\nAll the remaining project files are covered by the Apache license:\n\nCopyright (c) 2011-2019 Canonical Ltd\n\nLicensed under the Apache License, Version 2.0 (the \"License\");\nyou may not use this file except in compliance with the License.\nYou may obtain a copy of the License at\n\n    http://www.apache.org/licenses/LICENSE-2.0\n\nUnless required by applicable law or agreed to in writing, software\ndistributed under the License is distributed on an \"AS IS\" BASIS,\nWITHOUT WARRANTIES OR CONDITIONS OF ANY KIND, either express or implied.\nSee the License for the specific language governing permissions and\nlimitations under the License.\n",
      "checksums": [],
      "externalRefs": [
        {
          "referenceCategory": "PACKAGE-MANAGER",
          "referenceLocator": "pkg:golang/gopkg.in/yaml.v3@v3.0.1",
          "referenceType": "purl"
        }
      ]
    },
    {
      "SPDXID": "SPDXRef-Package-gomod-github.com-google-go-github-v50-v50.0.1-0.20230206142857-c855eb5fc7dc",
      "name": "github.com/google/go-github/v50",
      "versionInfo": "v50.0.1-0.20230206142857-c855eb5fc7dc",
      "filesAnalyzed": false,
      "licenseConcluded": "BSD-3-Clause",
      "downloadLocation": "https://proxy.golang.org/github.com/google/go-github/v50/@v/v50.0.1-0.20230206142857-c855eb5fc7dc.zip",
      "copyrightText": "Copyright (c) 2013 The go-github AUTHORS. All rights reserved.\n\nRedistribution and use in source and binary forms, with or without\nmodification, are permitted provided that the following conditions are\nmet:\n\n   * Redistributions of source code must retain the above copyright\nnotice, this list of conditions and the following disclaimer.\n   * Redistributions in binary form must reproduce the above\ncopyright notice, this list of conditions and the following disclaimer\nin the documentation and/or other materials provided with the\ndistribution.\n   * Neither the name of Google Inc. nor the names of its\ncontributors may be used to endorse or promote products derived from\nthis software without specific prior written permission.\n\nTHIS SOFTWARE IS PROVIDED BY THE COPYRIGHT HOLDERS AND CONTRIBUTORS\n\"AS IS\" AND ANY EXPRESS OR IMPLIED WARRANTIES, INCLUDING, BUT NOT\nLIMITED TO, THE IMPLIED WARRANTIES OF MERCHANTABILITY AND FITNESS FOR\nA PARTICULAR PURPOSE ARE DISCLAIMED. IN NO EVENT SHALL THE COPYRIGHT\nOWNER OR CONTRIBUTORS BE LIABLE FOR ANY DIRECT, INDIRECT, INCIDENTAL,\nSPECIAL, EXEMPLARY, OR CONSEQUENTIAL DAMAGES (INCLUDING, BUT NOT\nLIMITED TO, PROCUREMENT OF SUBSTITUTE GOODS OR SERVICES; LOSS OF USE,\nDATA, OR PROFITS; OR BUSINESS INTERRUPTION) HOWEVER CAUSED AND ON ANY\nTHEORY OF LIABILITY, WHETHER IN CONTRACT, STRICT LIABILITY, OR TORT\n(INCLUDING NEGLIGENCE OR OTHERWISE) ARISING IN ANY WAY OUT OF THE USE\nOF THIS SOFTWARE, EVEN IF ADVISED OF THE POSSIBILITY OF SUCH DAMAGE.\n",
      "checksums": [],
      "externalRefs": [
        {
          "referenceCategory": "PACKAGE-MANAGER",
          "referenceLocator": "pkg:golang/github.com/google/go-github/v50@v50.0.1-0.20230206142857-c855eb5fc7dc",
          "referenceType": "purl"
        }
      ]
    },
    {
      "SPDXID": "SPDXRef-Package-gomod-github.com-uber-jaeger-lib-v2.4.1C43incompatible",
      "name": "github.com/uber/jaeger-lib",
      "versionInfo": "v2.4.1",
      "filesAnalyzed": false,
      "licenseConcluded": "Apache-2.0",
      "downloadLocation": "git+https://github.com/uber/jaeger-lib",
      "copyrightText": "                                 Apache License\n                           Version 2.0, January 2004\n                        http://www.apache.org/licenses/\n\n   TERMS AND CONDITIONS FOR USE, REPRODUCTION, AND DISTRIBUTION\n\n   1. Definitions.\n\n      \"License\" shall mean the terms and conditions for use, reproduction,\n      and distribution as defined by Sections 1 through 9 of this document.\n\n      \"Licensor\" shall mean the copyright owner or entity authorized by\n      the copyright owner that is granting the License.\n\n      \"Legal Entity\" shall mean the union of the acting entity and all\n      other entities that control, are controlled by, or are under common\n      control with that entity. For the purposes of this definition,\n      \"control\" means (i) the power, direct or indirect, to cause the\n      direction or management of such entity, whether by contract or\n      otherwise, or (ii) ownership of fifty percent (50%) or more of the\n      outstanding shares, or (iii) beneficial ownership of such entity.\n\n      \"You\" (or \"Your\") shall mean an individual or Legal Entity\n      exercising permissions granted by this License.\n\n      \"Source\" form shall mean the preferred form for making modifications,\n      including but not limited to software source code, documentation\n      source, and configuration files.\n\n      \"Object\" form shall mean any form resulting from mechanical\n      transformation or translation of a Source form, including but\n      not limited to compiled object code, generated documentation,\n      and conversions to other media types.\n\n      \"Work\" shall mean the work of authorship, whether in Source or\n      Object form, made available under the License, as indicated by a\n      copyright notice that is included in or attached to the work\n      (an example is provided in the Appendix below).\n\n      \"Derivative Works\" shall mean any work, whether in Source or Object\n      form, that is based on (or derived from) the Work and for which the\n      editorial revisions, annotations, elaborations, or other modifications\n      represent, as a whole, an original work of authorship. For the purposes\n      of this License, Derivative Works shall not include works that remain\n      separable from, or merely link (or bind by name) to the interfaces of,\n      the Work and Derivative Works thereof.\n\n      \"Contribution\" shall mean any work of authorship, including\n      the original version of the Work and any modifications or additions\n      to that Work or Derivative Works thereof, that is intentionally\n      submitted to Licensor for inclusion in the Work by the copyright owner\n      or by an individual or Legal Entity authorized to submit on behalf of\n      the copyright owner. For the purposes of this definition, \"submitted\"\n      means any form of electronic, verbal, or written communication sent\n      to the Licensor or its representatives, including but not limited to\n      communication on electronic mailing lists, source code control systems,\n      and issue tracking systems that are managed by, or on behalf of, the\n      Licensor for the purpose of discussing and improving the Work, but\n      excluding communication that is conspicuously marked or otherwise\n      designated in writing by the copyright owner as \"Not a Contribution.\"\n\n      \"Contributor\" shall mean Licensor and any individual or Legal Entity\n      on behalf of whom a Contribution has been received by Licensor and\n      subsequently incorporated within the Work.\n\n   2. Grant of Copyright License. Subject to the terms and conditions of\n      this License, each Contributor hereby grants to You a perpetual,\n      worldwide, non-exclusive, no-charge, royalty-free, irrevocable\n      copyright license to reproduce, prepare Derivative Works of,\n      publicly display, publicly perform, sublicense, and distribute the\n      Work and such Derivative Works in Source or Object form.\n\n   3. Grant of Patent License. Subject to the terms and conditions of\n      this License, each Contributor hereby grants to You a perpetual,\n      worldwide, non-exclusive, no-charge, royalty-free, irrevocable\n      (except as stated in this section) patent license to make, have made,\n      use, offer to sell, sell, import, and otherwise transfer the Work,\n      where such license applies only to those patent claims licensable\n      by such Contributor that are necessarily infringed by their\n      Contribution(s) alone or by combination of their Contribution(s)\n      with the Work to which such Contribution(s) was submitted. If You\n      institute patent litigation against any entity (including a\n      cross-claim or counterclaim in a lawsuit) alleging that the Work\n      or a Contribution incorporated within the Work constitutes direct\n      or contributory patent infringement, then any patent licenses\n      granted to You under this License for that Work shall terminate\n      as of the date such litigation is filed.\n\n   4. Redistribution. You may reproduce and distribute copies of the\n      Work or Derivative Works thereof in any medium, with or without\n      modifications, and in Source or Object form, provided that You\n      meet the following conditions:\n\n      (a) You must give any other recipients of the Work or\n          Derivative Works a copy of this License; and\n\n      (b) You must cause any modified files to carry prominent notices\n          stating that You changed the files; and\n\n      (c) You must retain, in the Source form of any Derivative Works\n          that You distribute, all copyright, patent, trademark, and\n          attribution notices from the Source form of the Work,\n          excluding those notices that do not pertain to any part of\n          the Derivative Works; and\n\n      (d) If the Work includes a \"NOTICE\" text file as part of its\n          distribution, then any Derivative Works that You distribute must\n          include a readable copy of the attribution notices contained\n          within such NOTICE file, excluding those notices that do not\n          pertain to any part of the Derivative Works, in at least one\n          of the following places: within a NOTICE text file distributed\n          as part of the Derivative Works; within the Source form or\n          documentation, if provided along with the Derivative Works; or,\n          within a display generated by the Derivative Works, if and\n          wherever such third-party notices normally appear. The contents\n          of the NOTICE file are for informational purposes only and\n          do not modify the License. You may add Your own attribution\n          notices within Derivative Works that You distribute, alongside\n          or as an addendum to the NOTICE text from the Work, provided\n          that such additional attribution notices cannot be construed\n          as modifying the License.\n\n      You may add Your own copyright statement to Your modifications and\n      may provide additional or different license terms and conditions\n      for use, reproduction, or distribution of Your modifications, or\n      for any such Derivative Works as a whole, provided Your use,\n      reproduction, and distribution of the Work otherwise complies with\n      the conditions stated in this License.\n\n   5. Submission of Contributions. Unless You explicitly state otherwise,\n      any Contribution intentionally submitted for inclusion in the Work\n      by You to the Licensor shall be under the terms and conditions of\n      this License, without any additional terms or conditions.\n      Notwithstanding the above, nothing herein shall supersede or modify\n      the terms of any separate license agreement you may have executed\n      with Licensor regarding such Contributions.\n\n   6. Trademarks. This License does not grant permission to use the trade\n      names, trademarks, service marks, or product names of the Licensor,\n      except as required for reasonable and customary use in describing the\n      origin of the Work and reproducing the content of the NOTICE file.\n\n   7. Disclaimer of Warranty. Unless required by applicable law or\n      agreed to in writing, Licensor provides the Work (and each\n      Contributor provides its Contributions) on an \"AS IS\" BASIS,\n      WITHOUT WARRANTIES OR CONDITIONS OF ANY KIND, either express or\n      implied, including, without limitation, any warranties or conditions\n      of TITLE, NON-INFRINGEMENT, MERCHANTABILITY, or FITNESS FOR A\n      PARTICULAR PURPOSE. You are solely responsible for determining the\n      appropriateness of using or redistributing the Work and assume any\n      risks associated with Your exercise of permissions under this License.\n\n   8. Limitation of Liability. In no event and under no legal theory,\n      whether in tort (including negligence), contract, or otherwise,\n      unless required by applicable law (such as deliberate and grossly\n      negligent acts) or agreed to in writing, shall any Contributor be\n      liable to You for damages, including any direct, indirect, special,\n      incidental, or consequential damages of any character arising as a\n      result of this License or out of the use or inability to use the\n      Work (including but not limited to damages for loss of goodwill,\n      work stoppage, computer failure or malfunction, or any and all\n      other commercial damages or losses), even if such Contributor\n      has been advised of the possibility of such damages.\n\n   9. Accepting Warranty or Additional Liability. While redistributing\n      the Work or Derivative Works thereof, You may choose to offer,\n      and charge a fee for, acceptance of support, warranty, indemnity,\n      or other liability obligations and/or rights consistent with this\n      License. However, in accepting such obligations, You may act only\n      on Your own behalf and on Your sole responsibility, not on behalf\n      of any other Contributor, and only if You agree to indemnify,\n      defend, and hold each Contributor harmless for any liability\n      incurred by, or claims asserted against, such Contributor by reason\n      of your accepting any such warranty or additional liability.\n\n   END OF TERMS AND CONDITIONS\n\n   APPENDIX: How to apply the Apache License to your work.\n\n      To apply the Apache License to your work, attach the following\n      boilerplate notice, with the fields enclosed by brackets \"[]\"\n      replaced with your own identifying information. (Don't include\n      the brackets!)  The text should be enclosed in the appropriate\n      comment syntax for the file format. We also recommend that a\n      file or class name and description of purpose be included on the\n      same \"printed page\" as the copyright notice for easier\n      identification within third-party archives.\n\n   Copyright [yyyy] [name of copyright owner]\n\n   Licensed under the Apache License, Version 2.0 (the \"License\");\n   you may not use this file except in compliance with the License.\n   You may obtain a copy of the License at\n\n       http://www.apache.org/licenses/LICENSE-2.0\n\n   Unless required by applicable law or agreed to in writing, software\n   distributed under the License is distributed on an \"AS IS\" BASIS,\n   WITHOUT WARRANTIES OR CONDITIONS OF ANY KIND, either express or implied.\n   See the License for the specific language governing permissions and\n   limitations under the License.\n",
      "checksums": [],
      "externalRefs": [
        {
          "referenceCategory": "PACKAGE-MANAGER",
          "referenceLocator": "pkg:golang/github.com/uber/jaeger-lib@v2.4.1",
          "referenceType": "purl"
        }
      ]
    },
    {
      "SPDXID": "SPDXRef-Package-gomod-github.com-jamesruan-sodium-v1.0.14",
      "name": "github.com/jamesruan/sodium",
      "versionInfo": "v1.0.14",
      "filesAnalyzed": false,
      "licenseConcluded": "MIT",
      "downloadLocation": "https://proxy.golang.org/github.com/jamesruan/sodium/@v/v1.0.14.zip",
      "copyrightText": "The MIT License (MIT)\n\nCopyright (c) 2016 James Ruan <ruanbeihong@gmail.com>\n\nPermission is hereby granted, free of charge, to any person obtaining a copy\nof this software and associated documentation files (the \"Software\"), to deal\nin the Software without restriction, including without limitation the rights\nto use, copy, modify, merge, publish, distribute, sublicense, and/or sell\ncopies of the Software, and to permit persons to whom the Software is\nfurnished to do so, subject to the following conditions:\n\nThe above copyright notice and this permission notice shall be included in all\ncopies or substantial portions of the Software.\n\nTHE SOFTWARE IS PROVIDED \"AS IS\", WITHOUT WARRANTY OF ANY KIND, EXPRESS OR\nIMPLIED, INCLUDING BUT NOT LIMITED TO THE WARRANTIES OF MERCHANTABILITY,\nFITNESS FOR A PARTICULAR PURPOSE AND NONINFRINGEMENT. IN NO EVENT SHALL THE\nAUTHORS OR COPYRIGHT HOLDERS BE LIABLE FOR ANY CLAIM, DAMAGES OR OTHER\nLIABILITY, WHETHER IN AN ACTION OF CONTRACT, TORT OR OTHERWISE, ARISING FROM,\nOUT OF OR IN CONNECTION WITH THE SOFTWARE OR THE USE OR OTHER DEALINGS IN THE\nSOFTWARE.\n",
      "checksums": [],
      "externalRefs": [
        {
          "referenceCategory": "PACKAGE-MANAGER",
          "referenceLocator": "pkg:golang/github.com/jamesruan/sodium@v1.0.14",
          "referenceType": "purl"
        }
      ]
    },
    {
      "SPDXID": "SPDXRef-Package-gomod-github.com-uber-jaeger-client-go-v2.30.0C43incompatible",
      "name": "github.com/uber/jaeger-client-go",
      "versionInfo": "v2.30.0",
      "filesAnalyzed": false,
      "licenseConcluded": "Apache-2.0",
      "downloadLocation": "git+https://github.com/uber/jaeger-client-go",
      "copyrightText": "                                 Apache License\n                           Version 2.0, January 2004\n                        http://www.apache.org/licenses/\n\n   TERMS AND CONDITIONS FOR USE, REPRODUCTION, AND DISTRIBUTION\n\n   1. Definitions.\n\n      \"License\" shall mean the terms and conditions for use, reproduction,\n      and distribution as defined by Sections 1 through 9 of this document.\n\n      \"Licensor\" shall mean the copyright owner or entity authorized by\n      the copyright owner that is granting the License.\n\n      \"Legal Entity\" shall mean the union of the acting entity and all\n      other entities that control, are controlled by, or are under common\n      control with that entity. For the purposes of this definition,\n      \"control\" means (i) the power, direct or indirect, to cause the\n      direction or management of such entity, whether by contract or\n      otherwise, or (ii) ownership of fifty percent (50%) or more of the\n      outstanding shares, or (iii) beneficial ownership of such entity.\n\n      \"You\" (or \"Your\") shall mean an individual or Legal Entity\n      exercising permissions granted by this License.\n\n      \"Source\" form shall mean the preferred form for making modifications,\n      including but not limited to software source code, documentation\n      source, and configuration files.\n\n      \"Object\" form shall mean any form resulting from mechanical\n      transformation or translation of a Source form, including but\n      not limited to compiled object code, generated documentation,\n      and conversions to other media types.\n\n      \"Work\" shall mean the work of authorship, whether in Source or\n      Object form, made available under the License, as indicated by a\n      copyright notice that is included in or attached to the work\n      (an example is provided in the Appendix below).\n\n      \"Derivative Works\" shall mean any work, whether in Source or Object\n      form, that is based on (or derived from) the Work and for which the\n      editorial revisions, annotations, elaborations, or other modifications\n      represent, as a whole, an original work of authorship. For the purposes\n      of this License, Derivative Works shall not include works that remain\n      separable from, or merely link (or bind by name) to the interfaces of,\n      the Work and Derivative Works thereof.\n\n      \"Contribution\" shall mean any work of authorship, including\n      the original version of the Work and any modifications or additions\n      to that Work or Derivative Works thereof, that is intentionally\n      submitted to Licensor for inclusion in the Work by the copyright owner\n      or by an individual or Legal Entity authorized to submit on behalf of\n      the copyright owner. For the purposes of this definition, \"submitted\"\n      means any form of electronic, verbal, or written communication sent\n      to the Licensor or its representatives, including but not limited to\n      communication on electronic mailing lists, source code control systems,\n      and issue tracking systems that are managed by, or on behalf of, the\n      Licensor for the purpose of discussing and improving the Work, but\n      excluding communication that is conspicuously marked or otherwise\n      designated in writing by the copyright owner as \"Not a Contribution.\"\n\n      \"Contributor\" shall mean Licensor and any individual or Legal Entity\n      on behalf of whom a Contribution has been received by Licensor and\n      subsequently incorporated within the Work.\n\n   2. Grant of Copyright License. Subject to the terms and conditions of\n      this License, each Contributor hereby grants to You a perpetual,\n      worldwide, non-exclusive, no-charge, royalty-free, irrevocable\n      copyright license to reproduce, prepare Derivative Works of,\n      publicly display, publicly perform, sublicense, and distribute the\n      Work and such Derivative Works in Source or Object form.\n\n   3. Grant of Patent License. Subject to the terms and conditions of\n      this License, each Contributor hereby grants to You a perpetual,\n      worldwide, non-exclusive, no-charge, royalty-free, irrevocable\n      (except as stated in this section) patent license to make, have made,\n      use, offer to sell, sell, import, and otherwise transfer the Work,\n      where such license applies only to those patent claims licensable\n      by such Contributor that are necessarily infringed by their\n      Contribution(s) alone or by combination of their Contribution(s)\n      with the Work to which such Contribution(s) was submitted. If You\n      institute patent litigation against any entity (including a\n      cross-claim or counterclaim in a lawsuit) alleging that the Work\n      or a Contribution incorporated within the Work constitutes direct\n      or contributory patent infringement, then any patent licenses\n      granted to You under this License for that Work shall terminate\n      as of the date such litigation is filed.\n\n   4. Redistribution. You may reproduce and distribute copies of the\n      Work or Derivative Works thereof in any medium, with or without\n      modifications, and in Source or Object form, provided that You\n      meet the following conditions:\n\n      (a) You must give any other recipients of the Work or\n          Derivative Works a copy of this License; and\n\n      (b) You must cause any modified files to carry prominent notices\n          stating that You changed the files; and\n\n      (c) You must retain, in the Source form of any Derivative Works\n          that You distribute, all copyright, patent, trademark, and\n          attribution notices from the Source form of the Work,\n          excluding those notices that do not pertain to any part of\n          the Derivative Works; and\n\n      (d) If the Work includes a \"NOTICE\" text file as part of its\n          distribution, then any Derivative Works that You distribute must\n          include a readable copy of the attribution notices contained\n          within such NOTICE file, excluding those notices that do not\n          pertain to any part of the Derivative Works, in at least one\n          of the following places: within a NOTICE text file distributed\n          as part of the Derivative Works; within the Source form or\n          documentation, if provided along with the Derivative Works; or,\n          within a display generated by the Derivative Works, if and\n          wherever such third-party notices normally appear. The contents\n          of the NOTICE file are for informational purposes only and\n          do not modify the License. You may add Your own attribution\n          notices within Derivative Works that You distribute, alongside\n          or as an addendum to the NOTICE text from the Work, provided\n          that such additional attribution notices cannot be construed\n          as modifying the License.\n\n      You may add Your own copyright statement to Your modifications and\n      may provide additional or different license terms and conditions\n      for use, reproduction, or distribution of Your modifications, or\n      for any such Derivative Works as a whole, provided Your use,\n      reproduction, and distribution of the Work otherwise complies with\n      the conditions stated in this License.\n\n   5. Submission of Contributions. Unless You explicitly state otherwise,\n      any Contribution intentionally submitted for inclusion in the Work\n      by You to the Licensor shall be under the terms and conditions of\n      this License, without any additional terms or conditions.\n      Notwithstanding the above, nothing herein shall supersede or modify\n      the terms of any separate license agreement you may have executed\n      with Licensor regarding such Contributions.\n\n   6. Trademarks. This License does not grant permission to use the trade\n      names, trademarks, service marks, or product names of the Licensor,\n      except as required for reasonable and customary use in describing the\n      origin of the Work and reproducing the content of the NOTICE file.\n\n   7. Disclaimer of Warranty. Unless required by applicable law or\n      agreed to in writing, Licensor provides the Work (and each\n      Contributor provides its Contributions) on an \"AS IS\" BASIS,\n      WITHOUT WARRANTIES OR CONDITIONS OF ANY KIND, either express or\n      implied, including, without limitation, any warranties or conditions\n      of TITLE, NON-INFRINGEMENT, MERCHANTABILITY, or FITNESS FOR A\n      PARTICULAR PURPOSE. You are solely responsible for determining the\n      appropriateness of using or redistributing the Work and assume any\n      risks associated with Your exercise of permissions under this License.\n\n   8. Limitation of Liability. In no event and under no legal theory,\n      whether in tort (including negligence), contract, or otherwise,\n      unless required by applicable law (such as deliberate and grossly\n      negligent acts) or agreed to in writing, shall any Contributor be\n      liable to You for damages, including any direct, indirect, special,\n      incidental, or consequential damages of any character arising as a\n      result of this License or out of the use or inability to use the\n      Work (including but not limited to damages for loss of goodwill,\n      work stoppage, computer failure or malfunction, or any and all\n      other commercial damages or losses), even if such Contributor\n      has been advised of the possibility of such damages.\n\n   9. Accepting Warranty or Additional Liability. While redistributing\n      the Work or Derivative Works thereof, You may choose to offer,\n      and charge a fee for, acceptance of support, warranty, indemnity,\n      or other liability obligations and/or rights consistent with this\n      License. However, in accepting such obligations, You may act only\n      on Your own behalf and on Your sole responsibility, not on behalf\n      of any other Contributor, and only if You agree to indemnify,\n      defend, and hold each Contributor harmless for any liability\n      incurred by, or claims asserted against, such Contributor by reason\n      of your accepting any such warranty or additional liability.\n\n   END OF TERMS AND CONDITIONS\n\n   APPENDIX: How to apply the Apache License to your work.\n\n      To apply the Apache License to your work, attach the following\n      boilerplate notice, with the fields enclosed by brackets \"[]\"\n      replaced with your own identifying information. (Don't include\n      the brackets!)  The text should be enclosed in the appropriate\n      comment syntax for the file format. We also recommend that a\n      file or class name and description of purpose be included on the\n      same \"printed page\" as the copyright notice for easier\n      identification within third-party archives.\n\n   Copyright [yyyy] [name of copyright owner]\n\n   Licensed under the Apache License, Version 2.0 (the \"License\");\n   you may not use this file except in compliance with the License.\n   You may obtain a copy of the License at\n\n       http://www.apache.org/licenses/LICENSE-2.0\n\n   Unless required by applicable law or agreed to in writing, software\n   distributed under the License is distributed on an \"AS IS\" BASIS,\n   WITHOUT WARRANTIES OR CONDITIONS OF ANY KIND, either express or implied.\n   See the License for the specific language governing permissions and\n   limitations under the License.\n",
      "checksums": [],
      "externalRefs": [
        {
          "referenceCategory": "PACKAGE-MANAGER",
          "referenceLocator": "pkg:golang/github.com/uber/jaeger-client-go@v2.30.0",
          "referenceType": "purl"
        }
      ]
    },
    {
      "SPDXID": "SPDXRef-Package-gomod-go.uber.org-atomic-v1.9.0",
      "name": "go.uber.org/atomic",
      "versionInfo": "v1.9.0",
      "filesAnalyzed": false,
      "licenseConcluded": "MIT",
      "downloadLocation": "https://proxy.golang.org/go.uber.org/atomic/@v/v1.9.0.zip",
      "copyrightText": "Copyright (c) 2016 Uber Technologies, Inc.\n\nPermission is hereby granted, free of charge, to any person obtaining a copy\nof this software and associated documentation files (the \"Software\"), to deal\nin the Software without restriction, including without limitation the rights\nto use, copy, modify, merge, publish, distribute, sublicense, and/or sell\ncopies of the Software, and to permit persons to whom the Software is\nfurnished to do so, subject to the following conditions:\n\nThe above copyright notice and this permission notice shall be included in\nall copies or substantial portions of the Software.\n\nTHE SOFTWARE IS PROVIDED \"AS IS\", WITHOUT WARRANTY OF ANY KIND, EXPRESS OR\nIMPLIED, INCLUDING BUT NOT LIMITED TO THE WARRANTIES OF MERCHANTABILITY,\nFITNESS FOR A PARTICULAR PURPOSE AND NONINFRINGEMENT. IN NO EVENT SHALL THE\nAUTHORS OR COPYRIGHT HOLDERS BE LIABLE FOR ANY CLAIM, DAMAGES OR OTHER\nLIABILITY, WHETHER IN AN ACTION OF CONTRACT, TORT OR OTHERWISE, ARISING FROM,\nOUT OF OR IN CONNECTION WITH THE SOFTWARE OR THE USE OR OTHER DEALINGS IN\nTHE SOFTWARE.\n",
      "checksums": [],
      "externalRefs": [
        {
          "referenceCategory": "PACKAGE-MANAGER",
          "referenceLocator": "pkg:golang/go.uber.org/atomic@v1.9.0",
          "referenceType": "purl"
        }
      ]
    },
    {
      "SPDXID": "SPDXRef-Package-gomod-golang.org-x-crypto-v0.0.0-20210817164053-32db794688a5",
      "name": "golang.org/x/crypto",
      "versionInfo": "v0.0.0-20210817164053-32db794688a5",
      "filesAnalyzed": false,
      "licenseConcluded": "BSD-3-Clause",
      "downloadLocation": "https://proxy.golang.org/golang.org/x/crypto/@v/v0.0.0-20210817164053-32db794688a5.zip",
      "copyrightText": "Copyright (c) 2009 The Go Authors. All rights reserved.\n\nRedistribution and use in source and binary forms, with or without\nmodification, are permitted provided that the following conditions are\nmet:\n\n   * Redistributions of source code must retain the above copyright\nnotice, this list of conditions and the following disclaimer.\n   * Redistributions in binary form must reproduce the above\ncopyright notice, this list of conditions and the following disclaimer\nin the documentation and/or other materials provided with the\ndistribution.\n   * Neither the name of Google Inc. nor the names of its\ncontributors may be used to endorse or promote products derived from\nthis software without specific prior written permission.\n\nTHIS SOFTWARE IS PROVIDED BY THE COPYRIGHT HOLDERS AND CONTRIBUTORS\n\"AS IS\" AND ANY EXPRESS OR IMPLIED WARRANTIES, INCLUDING, BUT NOT\nLIMITED TO, THE IMPLIED WARRANTIES OF MERCHANTABILITY AND FITNESS FOR\nA PARTICULAR PURPOSE ARE DISCLAIMED. IN NO EVENT SHALL THE COPYRIGHT\nOWNER OR CONTRIBUTORS BE LIABLE FOR ANY DIRECT, INDIRECT, INCIDENTAL,\nSPECIAL, EXEMPLARY, OR CONSEQUENTIAL DAMAGES (INCLUDING, BUT NOT\nLIMITED TO, PROCUREMENT OF SUBSTITUTE GOODS OR SERVICES; LOSS OF USE,\nDATA, OR PROFITS; OR BUSINESS INTERRUPTION) HOWEVER CAUSED AND ON ANY\nTHEORY OF LIABILITY, WHETHER IN CONTRACT, STRICT LIABILITY, OR TORT\n(INCLUDING NEGLIGENCE OR OTHERWISE) ARISING IN ANY WAY OUT OF THE USE\nOF THIS SOFTWARE, EVEN IF ADVISED OF THE POSSIBILITY OF SUCH DAMAGE.\n",
      "checksums": [],
      "externalRefs": [
        {
          "referenceCategory": "PACKAGE-MANAGER",
          "referenceLocator": "pkg:golang/golang.org/x/crypto@v0.0.0-20210817164053-32db794688a5",
          "referenceType": "purl"
        }
      ]
    },
    {
      "SPDXID": "SPDXRef-Package-gomod-github.com-pkg-errors-v0.9.1",
      "name": "github.com/pkg/errors",
      "versionInfo": "v0.9.1",
      "filesAnalyzed": false,
      "licenseConcluded": "BSD-2-Clause",
      "downloadLocation": "https://proxy.golang.org/github.com/pkg/errors/@v/v0.9.1.zip",
      "copyrightText": "Copyright (c) 2015, Dave Cheney <dave@cheney.net>\nAll rights reserved.\n\nRedistribution and use in source and binary forms, with or without\nmodification, are permitted provided that the following conditions are met:\n\n* Redistributions of source code must retain the above copyright notice, this\n  list of conditions and the following disclaimer.\n\n* Redistributions in binary form must reproduce the above copyright notice,\n  this list of conditions and the following disclaimer in the documentation\n  and/or other materials provided with the distribution.\n\nTHIS SOFTWARE IS PROVIDED BY THE COPYRIGHT HOLDERS AND CONTRIBUTORS \"AS IS\"\nAND ANY EXPRESS OR IMPLIED WARRANTIES, INCLUDING, BUT NOT LIMITED TO, THE\nIMPLIED WARRANTIES OF MERCHANTABILITY AND FITNESS FOR A PARTICULAR PURPOSE ARE\nDISCLAIMED. IN NO EVENT SHALL THE COPYRIGHT HOLDER OR CONTRIBUTORS BE LIABLE\nFOR ANY DIRECT, INDIRECT, INCIDENTAL, SPECIAL, EXEMPLARY, OR CONSEQUENTIAL\nDAMAGES (INCLUDING, BUT NOT LIMITED TO, PROCUREMENT OF SUBSTITUTE GOODS OR\nSERVICES; LOSS OF USE, DATA, OR PROFITS; OR BUSINESS INTERRUPTION) HOWEVER\nCAUSED AND ON ANY THEORY OF LIABILITY, WHETHER IN CONTRACT, STRICT LIABILITY,\nOR TORT (INCLUDING NEGLIGENCE OR OTHERWISE) ARISING IN ANY WAY OUT OF THE USE\nOF THIS SOFTWARE, EVEN IF ADVISED OF THE POSSIBILITY OF SUCH DAMAGE.\n",
      "checksums": [],
      "externalRefs": [
        {
          "referenceCategory": "PACKAGE-MANAGER",
          "referenceLocator": "pkg:golang/github.com/pkg/errors@v0.9.1",
          "referenceType": "purl"
        }
      ]
    },
    {
      "SPDXID": "SPDXRef-Package-gomod-golang.org-x-oauth2-v0.0.0-20180821212333-d2e6202438be",
      "name": "golang.org/x/oauth2",
      "versionInfo": "v0.0.0-20180821212333-d2e6202438be",
      "filesAnalyzed": false,
      "licenseConcluded": "BSD-3-Clause",
      "downloadLocation": "https://proxy.golang.org/golang.org/x/oauth2/@v/v0.0.0-20180821212333-d2e6202438be.zip",
      "copyrightText": "Copyright (c) 2009 The Go Authors. All rights reserved.\n\nRedistribution and use in source and binary forms, with or without\nmodification, are permitted provided that the following conditions are\nmet:\n\n   * Redistributions of source code must retain the above copyright\nnotice, this list of conditions and the following disclaimer.\n   * Redistributions in binary form must reproduce the above\ncopyright notice, this list of conditions and the following disclaimer\nin the documentation and/or other materials provided with the\ndistribution.\n   * Neither the name of Google Inc. nor the names of its\ncontributors may be used to endorse or promote products derived from\nthis software without specific prior written permission.\n\nTHIS SOFTWARE IS PROVIDED BY THE COPYRIGHT HOLDERS AND CONTRIBUTORS\n\"AS IS\" AND ANY EXPRESS OR IMPLIED WARRANTIES, INCLUDING, BUT NOT\nLIMITED TO, THE IMPLIED WARRANTIES OF MERCHANTABILITY AND FITNESS FOR\nA PARTICULAR PURPOSE ARE DISCLAIMED. IN NO EVENT SHALL THE COPYRIGHT\nOWNER OR CONTRIBUTORS BE LIABLE FOR ANY DIRECT, INDIRECT, INCIDENTAL,\nSPECIAL, EXEMPLARY, OR CONSEQUENTIAL DAMAGES (INCLUDING, BUT NOT\nLIMITED TO, PROCUREMENT OF SUBSTITUTE GOODS OR SERVICES; LOSS OF USE,\nDATA, OR PROFITS; OR BUSINESS INTERRUPTION) HOWEVER CAUSED AND ON ANY\nTHEORY OF LIABILITY, WHETHER IN CONTRACT, STRICT LIABILITY, OR TORT\n(INCLUDING NEGLIGENCE OR OTHERWISE) ARISING IN ANY WAY OUT OF THE USE\nOF THIS SOFTWARE, EVEN IF ADVISED OF THE POSSIBILITY OF SUCH DAMAGE.\n",
      "checksums": [],
      "externalRefs": [
        {
          "referenceCategory": "PACKAGE-MANAGER",
          "referenceLocator": "pkg:golang/golang.org/x/oauth2@v0.0.0-20180821212333-d2e6202438be",
          "referenceType": "purl"
        }
      ]
    }
  ],
  "relationships": [
    {
      "spdxElementId": "SPDXRef-Package-tmp.CvHgx0WVyh",
      "relationshipType": "CONTAINS",
      "relatedSpdxElement": "SPDXRef-File-tmp.CvHgx0WVyh-.gitignore"
    },
    {
      "spdxElementId": "SPDXRef-Package-tmp.CvHgx0WVyh",
      "relationshipType": "CONTAINS",
      "relatedSpdxElement": "SPDXRef-File-tmp.CvHgx0WVyh-.github-workflows-release.yaml"
    },
    {
      "spdxElementId": "SPDXRef-Package-tmp.CvHgx0WVyh",
      "relationshipType": "CONTAINS",
      "relatedSpdxElement": "SPDXRef-File-tmp.CvHgx0WVyh-.github-workflows-ci.yaml"
    },
    {
      "spdxElementId": "SPDXRef-Package-tmp.CvHgx0WVyh",
      "relationshipType": "CONTAINS",
      "relatedSpdxElement": "SPDXRef-File-tmp.CvHgx0WVyh-.goreleaser.yml"
    },
    {
      "spdxElementId": "SPDXRef-Package-tmp.CvHgx0WVyh",
      "relationshipType": "CONTAINS",
      "relatedSpdxElement": "SPDXRef-File-tmp.CvHgx0WVyh-OWNERS"
    },
    {
      "spdxElementId": "SPDXRef-Package-tmp.CvHgx0WVyh",
      "relationshipType": "CONTAINS",
      "relatedSpdxElement": "SPDXRef-File-tmp.CvHgx0WVyh-Makefile"
    },
    {
      "spdxElementId": "SPDXRef-Package-tmp.CvHgx0WVyh",
      "relationshipType": "CONTAINS",
      "relatedSpdxElement": "SPDXRef-File-tmp.CvHgx0WVyh-README.md"
    },
    {
      "spdxElementId": "SPDXRef-Package-tmp.CvHgx0WVyh",
      "relationshipType": "CONTAINS",
      "relatedSpdxElement": "SPDXRef-File-tmp.CvHgx0WVyh-go.mod"
    },
    {
      "spdxElementId": "SPDXRef-Package-tmp.CvHgx0WVyh",
      "relationshipType": "CONTAINS",
      "relatedSpdxElement": "SPDXRef-File-tmp.CvHgx0WVyh-go.sum"
    },
    {
      "spdxElementId": "SPDXRef-Package-tmp.CvHgx0WVyh",
      "relationshipType": "CONTAINS",
      "relatedSpdxElement": "SPDXRef-File-tmp.CvHgx0WVyh-LICENSE"
    },
    {
      "spdxElementId": "SPDXRef-Package-tmp.CvHgx0WVyh",
      "relationshipType": "CONTAINS",
      "relatedSpdxElement": "SPDXRef-File-tmp.CvHgx0WVyh-main.go"
    },
    {
      "spdxElementId": "SPDXRef-Package-tmp.CvHgx0WVyh",
      "relationshipType": "CONTAINS",
      "relatedSpdxElement": "SPDXRef-File-tmp.CvHgx0WVyh-pkg-config-config.go"
    },
    {
      "spdxElementId": "SPDXRef-Package-tmp.CvHgx0WVyh",
      "relationshipType": "CONTAINS",
      "relatedSpdxElement": "SPDXRef-File-tmp.CvHgx0WVyh-pkg-poiana-secrets.go"
    },
    {
      "spdxElementId": "SPDXRef-Package-tmp.CvHgx0WVyh",
      "relationshipType": "CONTAINS",
      "relatedSpdxElement": "SPDXRef-File-tmp.CvHgx0WVyh-.github-PULLC95REQUESTC95TEMPLATE.md"
    },
    {
      "spdxElementId": "SPDXRef-Package-tmp.CvHgx0WVyh",
      "relationshipType": "CONTAINS",
      "relatedSpdxElement": "SPDXRef-File-tmp.CvHgx0WVyh-pkg-poiana-secretsC95client.go"
    },
    {
      "spdxElementId": "SPDXRef-Package-tmp.CvHgx0WVyh",
      "relationshipType": "CONTAINS",
      "relatedSpdxElement": "SPDXRef-File-tmp.CvHgx0WVyh-pkg-poiana-serviceC95factory.go"
    },
    {
      "spdxElementId": "SPDXRef-Package-tmp.CvHgx0WVyh",
      "relationshipType": "CONTAINS",
      "relatedSpdxElement": "SPDXRef-File-tmp.CvHgx0WVyh-pkg-poiana-secretsC95mock.go"
    },
    {
      "spdxElementId": "SPDXRef-Package-tmp.CvHgx0WVyh",
      "relationshipType": "CONTAINS",
      "relatedSpdxElement": "SPDXRef-File-tmp.CvHgx0WVyh-pkg-poiana-secretsC95onepassword.go"
    },
    {
      "spdxElementId": "SPDXRef-Package-tmp.CvHgx0WVyh",
      "relationshipType": "CONTAINS",
      "relatedSpdxElement": "SPDXRef-File-tmp.CvHgx0WVyh-pkg-config-configC95test.go"
    },
    {
      "spdxElementId": "SPDXRef-Package-tmp.CvHgx0WVyh",
      "relationshipType": "CONTAINS",
      "relatedSpdxElement": "SPDXRef-File-tmp.CvHgx0WVyh-pkg-poiana-serviceC95factoryC95mock.go"
    },
    {
      "spdxElementId": "SPDXRef-Package-tmp.CvHgx0WVyh",
      "relationshipType": "CONTAINS",
      "relatedSpdxElement": "SPDXRef-File-tmp.CvHgx0WVyh-pkg-poiana-variables.go"
    },
    {
      "spdxElementId": "SPDXRef-Package-tmp.CvHgx0WVyh",
      "relationshipType": "CONTAINS",
      "relatedSpdxElement": "SPDXRef-File-tmp.CvHgx0WVyh-pkg-poiana-variablesC95mock.go"
    },
    {
      "spdxElementId": "SPDXRef-Package-tmp.CvHgx0WVyh",
      "relationshipType": "CONTAINS",
      "relatedSpdxElement": "SPDXRef-File-tmp.CvHgx0WVyh-pkg-poiana-variablesC95client.go"
    },
    {
      "spdxElementId": "SPDXRef-Package-tmp.CvHgx0WVyh",
      "relationshipType": "CONTAINS",
      "relatedSpdxElement": "SPDXRef-File-tmp.CvHgx0WVyh-release.md"
    },
    {
      "spdxElementId": "SPDXRef-Package-tmp.CvHgx0WVyh",
      "relationshipType": "CONTAINS",
      "relatedSpdxElement": "SPDXRef-File-tmp.CvHgx0WVyh-pkg-poiana-serviceC95factoryC95client.go"
    },
    {
      "spdxElementId": "SPDXRef-Package-tmp.CvHgx0WVyh",
      "relationshipType": "DEPENDS_ON",
      "relatedSpdxElement": "SPDXRef-Package-gomod-github.com-google-go-github-v50-v50.0.1-0.20230206142857-c855eb5fc7dc"
    },
    {
      "spdxElementId": "SPDXRef-Package-tmp.CvHgx0WVyh",
      "relationshipType": "DEPENDS_ON",
      "relatedSpdxElement": "SPDXRef-Package-gomod-github.com-1Password-connect-sdk-go-v1.5.0"
    },
    {
      "spdxElementId": "SPDXRef-Package-tmp.CvHgx0WVyh",
      "relationshipType": "DEPENDS_ON",
      "relatedSpdxElement": "SPDXRef-Package-gomod-github.com-uber-jaeger-lib-v2.4.1C43incompatible"
    },
    {
      "spdxElementId": "SPDXRef-Package-tmp.CvHgx0WVyh",
      "relationshipType": "DEPENDS_ON",
      "relatedSpdxElement": "SPDXRef-Package-gomod-golang.org-x-crypto-v0.0.0-20210817164053-32db794688a5"
    },
    {
      "spdxElementId": "SPDXRef-Package-tmp.CvHgx0WVyh",
      "relationshipType": "DEPENDS_ON",
      "relatedSpdxElement": "SPDXRef-Package-gomod-golang.org-x-oauth2-v0.0.0-20180821212333-d2e6202438be"
    },
    {
      "spdxElementId": "SPDXRef-Package-tmp.CvHgx0WVyh",
      "relationshipType": "DEPENDS_ON",
      "relatedSpdxElement": "SPDXRef-Package-gomod-golang.org-x-sys-v0.0.0-20220715151400-c0bba94af5f8"
    },
    {
      "spdxElementId": "SPDXRef-Package-tmp.CvHgx0WVyh",
      "relationshipType": "DEPENDS_ON",
      "relatedSpdxElement": "SPDXRef-Package-gomod-github.com-pkg-errors-v0.9.1"
    },
    {
      "spdxElementId": "SPDXRef-Package-tmp.CvHgx0WVyh",
      "relationshipType": "DEPENDS_ON",
      "relatedSpdxElement": "SPDXRef-Package-gomod-go.uber.org-atomic-v1.9.0"
    },
    {
      "spdxElementId": "SPDXRef-Package-tmp.CvHgx0WVyh",
      "relationshipType": "DEPENDS_ON",
      "relatedSpdxElement": "SPDXRef-Package-gomod-golang.org-x-net-v0.0.0-20210226172049-e18ecbb05110"
    },
    {
      "spdxElementId": "SPDXRef-Package-tmp.CvHgx0WVyh",
      "relationshipType": "DEPENDS_ON",
      "relatedSpdxElement": "SPDXRef-Package-gomod-github.com-sirupsen-logrus-v1.9.0"
    },
    {
      "spdxElementId": "SPDXRef-Package-tmp.CvHgx0WVyh",
      "relationshipType": "DEPENDS_ON",
      "relatedSpdxElement": "SPDXRef-Package-gomod-github.com-jamesruan-sodium-v1.0.14"
    },
    {
      "spdxElementId": "SPDXRef-Package-tmp.CvHgx0WVyh",
      "relationshipType": "DEPENDS_ON",
      "relatedSpdxElement": "SPDXRef-Package-gomod-gopkg.in-yaml.v3-v3.0.1"
    },
    {
      "spdxElementId": "SPDXRef-Package-tmp.CvHgx0WVyh",
      "relationshipType": "DEPENDS_ON",
      "relatedSpdxElement": "SPDXRef-Package-gomod-github.com-opentracing-opentracing-go-v1.2.0"
    },
    {
      "spdxElementId": "SPDXRef-Package-tmp.CvHgx0WVyh",
      "relationshipType": "DEPENDS_ON",
      "relatedSpdxElement": "SPDXRef-Package-gomod-github.com-uber-jaeger-client-go-v2.30.0C43incompatible"
    },
    {
      "spdxElementId": "SPDXRef-Package-tmp.CvHgx0WVyh",
      "relationshipType": "DEPENDS_ON",
      "relatedSpdxElement": "SPDXRef-Package-gomod-github.com-google-go-querystring-v1.1.0"
    }
  ],
  "annotations": [
    {
      "annotationDate": "2026-02-14T02:51:47Z",
      "annotationType": "OTHER",
      "annotator": "Tool: cncf-automation",
      "comment": "Repository: falcosecurity/pigeon\nVersion: v0.2.1"
    }
  ],
  "hasExtractedLicensingInfo": [
    {
      "licenseId": "LicenseRef-github-com-1Password-connect-sdk-go",
      "extractedText": "License: MIT",
      "name": "MIT",
      "comment": "Package: github.com/1Password/connect-sdk-go"
    },
    {
      "licenseId": "LicenseRef-github-com-FedeDP-Pigeon",
      "extractedText": "License: Apache-2.0",
      "name": "Apache-2.0",
      "comment": "Package: github.com/FedeDP/Pigeon"
    },
    {
      "licenseId": "LicenseRef-github-com-google-go-github-v50-github",
      "extractedText": "License: BSD-3-Clause",
      "name": "BSD-3-Clause",
      "comment": "Package: github.com/google/go-github/v50/github"
    },
    {
      "licenseId": "LicenseRef-github-com-google-go-querystring-query",
      "extractedText": "License: BSD-3-Clause",
      "name": "BSD-3-Clause",
      "comment": "Package: github.com/google/go-querystring/query"
    },
    {
      "licenseId": "LicenseRef-github-com-jamesruan-sodium",
      "extractedText": "License: MIT",
      "name": "MIT",
      "comment": "Package: github.com/jamesruan/sodium"
    },
    {
      "licenseId": "LicenseRef-github-com-opentracing-opentracing-go",
      "extractedText": "License: Apache-2.0",
      "name": "Apache-2.0",
      "comment": "Package: github.com/opentracing/opentracing-go"
    },
    {
      "licenseId": "LicenseRef-github-com-pkg-errors",
      "extractedText": "License: BSD-2-Clause",
      "name": "BSD-2-Clause",
      "comment": "Package: github.com/pkg/errors"
    },
    {
      "licenseId": "LicenseRef-github-com-sirupsen-logrus",
      "extractedText": "License: MIT",
      "name": "MIT",
      "comment": "Package: github.com/sirupsen/logrus"
    },
    {
      "licenseId": "LicenseRef-github-com-uber-jaeger-client-go",
      "extractedText": "License: Apache-2.0",
      "name": "Apache-2.0",
      "comment": "Package: github.com/uber/jaeger-client-go"
    },
    {
      "licenseId": "LicenseRef-github-com-uber-jaeger-lib-metrics",
      "extractedText": "License: Apache-2.0",
      "name": "Apache-2.0",
      "comment": "Package: github.com/uber/jaeger-lib/metrics"
    },
    {
      "licenseId": "LicenseRef-go-uber-org-atomic",
      "extractedText": "License: MIT",
      "name": "MIT",
      "comment": "Package: go.uber.org/atomic"
    },
    {
      "licenseId": "LicenseRef-golang-org-x-crypto",
      "extractedText": "License: BSD-3-Clause",
      "name": "BSD-3-Clause",
      "comment": "Package: golang.org/x/crypto"
    },
    {
      "licenseId": "LicenseRef-golang-org-x-net-context",
      "extractedText": "License: BSD-3-Clause",
      "name": "BSD-3-Clause",
      "comment": "Package: golang.org/x/net/context"
    },
    {
      "licenseId": "LicenseRef-golang-org-x-oauth2",
      "extractedText": "License: BSD-3-Clause",
      "name": "BSD-3-Clause",
      "comment": "Package: golang.org/x/oauth2"
    },
    {
      "licenseId": "LicenseRef-golang-org-x-sys",
      "extractedText": "License: BSD-3-Clause",
      "name": "BSD-3-Clause",
      "comment": "Package: golang.org/x/sys"
    },
    {
      "licenseId": "LicenseRef-gopkg-in-yaml-v3",
      "extractedText": "License: MIT",
      "name": "MIT",
      "comment": "Package: gopkg.in/yaml.v3"
    }
  ]
}
